{"date":"2013-10-22","rows":[{"n":"PALLADIUM - NEW YORK MERCANTILE EXCHANGE","c":"075651","oi":37936,"mp":62.6,"cp":-8.24,"P":-30,"F":-40,"co":-17.5,"L":41,"fl":""},{"n":"HENRY HUB - TAILGATE, LOUISIANA (INDEX) - ICE FUTURES ENERGY DIV","c":"0233AH","oi":162658,"mp":40.5,"cp":-5.15,"P":-30,"F":-30,"co":-15.0,"L":43,"fl":""},{"n":"PLATINUM - NEW YORK MERCANTILE EXCHANGE","c":"076651","oi":58993,"mp":35.2,"cp":-4.11,"P":-20,"F":-40,"co":-15.0,"L":43,"fl":""},{"n":"HENRY HUB - TAILGATE, LOUISIANA (BASIS) - ICE FUTURES ENERGY DIV","c":"0233AG","oi":165719,"mp":31.1,"cp":-5.34,"P":-20,"F":-30,"co":-12.5,"L":44,"fl":""},{"n":"COPPER-GRADE #1 - COMMODITY EXCHANGE INC.","c":"085692","oi":154924,"mp":12.0,"cp":-8.26,"P":-10,"F":-40,"co":-12.5,"L":44,"fl":""},{"n":"SILVER - COMMODITY EXCHANGE INC.","c":"084691","oi":116767,"mp":15.1,"cp":-4.81,"P":-10,"F":-40,"co":-12.5,"L":44,"fl":""},{"n":"GOLD - COMMODITY EXCHANGE INC.","c":"088691","oi":390369,"mp":17.1,"cp":-4.44,"P":-10,"F":-30,"co":-10.0,"L":45,"fl":""},{"n":"LIVE CATTLE - CHICAGO MERCANTILE EXCHANGE","c":"057642","oi":322415,"mp":25.5,"cp":-0.81,"P":-20,"F":-20,"co":-10.0,"L":45,"fl":""},{"n":"NATURAL GAS INDEX: ALGONQUIN CITY GATES - ICE FUTURES ENERGY DIV","c":"0233AW","oi":17845,"mp":8.7,"cp":-25.44,"P":0,"F":-40,"co":-10.0,"L":45,"fl":""},{"n":"SUGAR NO. 11 - ICE FUTURES U.S.","c":"080732","oi":830021,"mp":20.6,"cp":-1.84,"P":-10,"F":-20,"co":-7.5,"L":46,"fl":""},{"n":"NYISO ZONE A 5MW OFF PEAK SWAP - NEW YORK MERCANTILE EXCHANGE","c":"064A82","oi":610370,"mp":0.0,"cp":-7.67,"P":0,"F":-30,"co":-7.5,"L":46,"fl":"MM0"},{"n":"NYISO ZONE J5 MW OFF PEAK SWAP - NEW YORK MERCANTILE EXCHANGE","c":"064A85","oi":328343,"mp":-0.8,"cp":-7.1,"P":0,"F":-30,"co":-7.5,"L":46,"fl":""},{"n":"SOYBEAN OIL - CHICAGO BOARD OF TRADE","c":"007601","oi":322364,"mp":-5.9,"cp":-4.26,"P":0,"F":-30,"co":-7.5,"L":46,"fl":""},{"n":"LEAN HOGS - CHICAGO MERCANTILE EXCHANGE","c":"054642","oi":295511,"mp":30.2,"cp":-0.64,"P":-20,"F":-10,"co":-7.5,"L":46,"fl":""},{"n":"NPATH 15 EZ GEN HUB DA OFFPEAK - ICE FUTURES ENERGY DIV","c":"0643BR","oi":261140,"mp":38.1,"cp":-2.49,"P":-20,"F":-10,"co":-7.5,"L":46,"fl":""},{"n":"COCOA - ICE FUTURES U.S.","c":"073732","oi":226213,"mp":32.5,"cp":-0.5,"P":-20,"F":-10,"co":-7.5,"L":46,"fl":""},{"n":"WHEAT - KANSAS CITY BOARD OF TRADE","c":"001612","oi":158135,"mp":27.3,"cp":-0.68,"P":-20,"F":-10,"co":-7.5,"L":46,"fl":""},{"n":"TRANSCONTINENTAL GAS - ZONE 6 (NY) (BASIS) - ICE FUTURES ENERGY DIV","c":"0233CZ","oi":92414,"mp":-13.3,"cp":-4.3,"P":10,"F":-40,"co":-7.5,"L":46,"fl":""},{"n":"NYISO ZONE A 5 MW PEAK SWAP - NEW YORK MERCANTILE EXCHANGE","c":"064A66","oi":43137,"mp":0.0,"cp":-5.91,"P":0,"F":-30,"co":-7.5,"L":46,"fl":"MM0"},{"n":"NORTHERN ILLINOIS HUB (REAL TIME LMP) - ICE FUTURES ENERGY DIV","c":"0643BT","oi":36618,"mp":10.9,"cp":-3.77,"P":-10,"F":-20,"co":-7.5,"L":46,"fl":""},{"n":"OATS - CHICAGO BOARD OF TRADE","c":"004603","oi":10174,"mp":3.9,"cp":-7.45,"P":0,"F":-30,"co":-7.5,"L":46,"fl":""},{"n":"SOYBEANS - CHICAGO BOARD OF TRADE","c":"005602","oi":652100,"mp":21.1,"cp":-1.12,"P":-10,"F":-10,"co":-5.0,"L":48,"fl":""},{"n":"CRUDE OIL, LIGHT SWEET - ICE FUTURES EUROPE","c":"067411","oi":603196,"mp":9.9,"cp":-2.91,"P":0,"F":-20,"co":-5.0,"L":48,"fl":""},{"n":"SOYBEAN MEAL - CHICAGO BOARD OF TRADE","c":"026603","oi":277326,"mp":19.3,"cp":-2.25,"P":-10,"F":-10,"co":-5.0,"L":48,"fl":""},{"n":"SOCAL BORDER FIN BASIS - ICE FUTURES ENERGY DIV","c":"023393","oi":232365,"mp":2.3,"cp":-0.4,"P":0,"F":-20,"co":-5.0,"L":48,"fl":""},{"n":"GASOLINE BLENDSTOCK (RBOB) - NEW YORK MERCANTILE EXCHANGE","c":"111659","oi":232115,"mp":13.1,"cp":-0.67,"P":-10,"F":-10,"co":-5.0,"L":48,"fl":""},{"n":"COAL (API 2) CIF ARA SWAP FUT - NEW YORK MERCANTILE EXCHANGE","c":"024656","oi":79871,"mp":-2.9,"cp":-3.07,"P":0,"F":-20,"co":-5.0,"L":48,"fl":""},{"n":"COLORADO INTERSTATE - MAINLINE (BASIS) - ICE FUTURES ENERGY DIV","c":"02339U","oi":78373,"mp":-6.7,"cp":-2.68,"P":0,"F":-20,"co":-5.0,"L":48,"fl":""},{"n":"WAHA FIN BASIS - ICE FUTURES ENERGY DIV","c":"023399","oi":70140,"mp":9.8,"cp":-0.83,"P":0,"F":-20,"co":-5.0,"L":48,"fl":""},{"n":"FEEDER CATTLE - CHICAGO MERCANTILE EXCHANGE","c":"061641","oi":38595,"mp":25.8,"cp":-0.95,"P":-20,"F":0,"co":-5.0,"L":48,"fl":""},{"n":"HENRY HUB SWAP - NEW YORK MERCANTILE EXCHANGE","c":"03565B","oi":2632545,"mp":10.1,"cp":0.01,"P":-10,"F":0,"co":-2.5,"L":49,"fl":""},{"n":"CRUDE OIL, LIGHT SWEET - NEW YORK MERCANTILE EXCHANGE","c":"067651","oi":1785295,"mp":12.8,"cp":0.04,"P":-10,"F":0,"co":-2.5,"L":49,"fl":""},{"n":"PJM AEP DAYTON OFF PEAK SWAP - NEW YORK MERCANTILE EXCHANGE","c":"064A80","oi":1205951,"mp":21.8,"cp":0.0,"P":-10,"F":0,"co":-2.5,"L":49,"fl":""},{"n":"HENRY HUB PENULTIMATE GAS SWAP - NEW YORK MERCANTILE EXCHANGE","c":"03565C","oi":868617,"mp":-3.0,"cp":-1.19,"P":0,"F":-10,"co":-2.5,"L":49,"fl":""},{"n":"NEPOOL MASS HUB (DAY-AHEAD LMP OFF-PEAK) - ICE FUTURES ENERGY DIV","c":"0643BF","oi":605275,"mp":20.3,"cp":-0.12,"P":-10,"F":0,"co":-2.5,"L":49,"fl":""},{"n":"WHEAT - CHICAGO BOARD OF TRADE","c":"001602","oi":374948,"mp":7.4,"cp":-1.26,"P":0,"F":-10,"co":-2.5,"L":49,"fl":""},{"n":"DOMINION - SOUTH POINT (BASIS) - ICE FUTURES ENERGY DIV","c":"0233A3","oi":324372,"mp":0.1,"cp":-0.57,"P":0,"F":-10,"co":-2.5,"L":49,"fl":""},{"n":"NYISO ZONE  A  (OFF-PEAK) - ICE FUTURES ENERGY DIV","c":"0643BZ","oi":312530,"mp":1.5,"cp":-0.38,"P":0,"F":-10,"co":-2.5,"L":49,"fl":""},{"n":"CIN HUB REAL TIME OFF-PEAK - ICE FUTURES ENERGY DIV","c":"06439L","oi":282496,"mp":3.9,"cp":-0.43,"P":0,"F":-10,"co":-2.5,"L":49,"fl":""},{"n":"WTI CRUDE OIL CALENDAR SWAP - NEW YORK MERCANTILE EXCHANGE","c":"06765A","oi":161136,"mp":-2.5,"cp":-1.3,"P":0,"F":-10,"co":-2.5,"L":49,"fl":""},{"n":"PACIFIC GAS TRANSMISSION - MALIN (BASIS) - ICE FUTURES ENERGY DIV","c":"0233BH","oi":107260,"mp":-2.0,"cp":-1.7,"P":0,"F":-10,"co":-2.5,"L":49,"fl":""},{"n":"NORTHERN NATURAL GAS - VENTURA (BASIS) - ICE FUTURES ENERGY DIV","c":"0233BB","oi":99714,"mp":2.7,"cp":-1.12,"P":0,"F":-10,"co":-2.5,"L":49,"fl":""},{"n":"PJM AEP DAY HUB 5 MW PEAK SWAP - NEW YORK MERCANTILE EXCHANGE","c":"064A64","oi":51007,"mp":10.2,"cp":0.32,"P":-10,"F":0,"co":-2.5,"L":49,"fl":""},{"n":"WHEAT - MINNEAPOLIS GRAIN EXCHANGE","c":"001626","oi":50399,"mp":6.3,"cp":-2.43,"P":0,"F":-10,"co":-2.5,"L":49,"fl":""},{"n":"GULF # 6 FUEL 3.0% SULFUR SWAP - NEW YORK MERCANTILE EXCHANGE","c":"02165A","oi":42440,"mp":0.0,"cp":-1.48,"P":0,"F":-10,"co":-2.5,"L":49,"fl":"MM0"},{"n":"NEPOOL MASS HUB (DAY-AHEAD LMP) - ICE FUTURES ENERGY DIV","c":"0643BG","oi":41726,"mp":11.7,"cp":0.23,"P":-10,"F":0,"co":-2.5,"L":49,"fl":""},{"n":"N PATH 15 EZ GEN HUB DA PEAK - ICE FUTURES ENERGY DIV","c":"0643BM","oi":25332,"mp":18.6,"cp":-1.01,"P":-10,"F":0,"co":-2.5,"L":49,"fl":""},{"n":"CALIF CARBON ALLOWANCE-2013 - ICE FUTURES ENERGY DIV","c":"006391","oi":9244,"mp":14.1,"cp":1.75,"P":-10,"F":0,"co":-2.5,"L":49,"fl":"ENV"},{"n":"AEP DAYTON PEAKCAL MONTH LMP 5 - NEW YORK MERCANTILE EXCHANGE","c":"06465K","oi":8493,"mp":15.4,"cp":0.0,"P":-10,"F":0,"co":-2.5,"L":49,"fl":""},{"n":"ISO NEW ENGLAND LMP SWAP - NEW YORK MERCANTILE EXCHANGE","c":"06465H","oi":7698,"mp":20.0,"cp":0.0,"P":-10,"F":0,"co":-2.5,"L":49,"fl":""},{"n":"PJM WESTERN HUB (DAY-AHEAD OFF PEAK) - ICE FUTURES ENERGY DIV","c":"0643DB","oi":7026712,"mp":1.7,"cp":0.0,"P":0,"F":0,"co":0.0,"L":50,"fl":""},{"n":"PJM WH REAL TIME MINI OFF-PEAK - ICE FUTURES ENERGY DIV","c":"0643DK","oi":6410394,"mp":-0.6,"cp":0.0,"P":0,"F":0,"co":0.0,"L":50,"fl":""},{"n":"NATURAL GAS ICE HENRY HUB - ICE FUTURES ENERGY DIV","c":"023391","oi":5609172,"mp":11.2,"cp":0.72,"P":-10,"F":10,"co":0.0,"L":50,"fl":""},{"n":"PJM WESTERN HUB MINI (REAL TIME LMP) - ICE FUTURES ENERGY DIV","c":"0643DF","oi":2938232,"mp":-4.8,"cp":0.27,"P":0,"F":0,"co":0.0,"L":50,"fl":""},{"n":"PJM WESTERN HUB (DAY-AHEAD) - ICE FUTURES ENERGY DIV","c":"0643DC","oi":2261650,"mp":0.9,"cp":0.0,"P":0,"F":0,"co":0.0,"L":50,"fl":""},{"n":"PSB-PJM PSEG ZONE DAY-AHEAD OFF-PEAK - ICE FUTURES ENERGY DIV","c":"0643DM","oi":2142732,"mp":-0.2,"cp":0.0,"P":0,"F":0,"co":0.0,"L":50,"fl":""},{"n":"AD HUB DA OFF-PEAK MONTHLY - ICE FUTURES ENERGY DIV","c":"06439C","oi":1852025,"mp":0.0,"cp":0.0,"P":0,"F":0,"co":0.0,"L":50,"fl":"MM0"},{"n":"PJM WH OFF PEAK REAL TIME - ICE FUTURES ENERGY DIV","c":"064394","oi":1635018,"mp":3.9,"cp":0.29,"P":0,"F":0,"co":0.0,"L":50,"fl":""},{"n":"NATURAL GAS - NEW YORK MERCANTILE EXCHANGE","c":"023651","oi":1261740,"mp":1.1,"cp":-0.23,"P":0,"F":0,"co":0.0,"L":50,"fl":""},{"n":"ERCOT - NORTH MONTHLY OFF-PEAK - ICE FUTURES ENERGY DIV","c":"0643A8","oi":1165075,"mp":2.4,"cp":0.0,"P":0,"F":0,"co":0.0,"L":50,"fl":""},{"n":"N. ILLINOIS HUB DAY AHEAD LMP, OFF PEAK MONTHLY - ICE FUTURES ENERGY DIV","c":"0643BC","oi":1068811,"mp":0.0,"cp":0.0,"P":0,"F":0,"co":0.0,"L":50,"fl":"MM0"},{"n":"PJM PPL ZONE DAY AHEAD, OFF-PEAK MONTHLY - ICE FUTURES ENERGY DIV","c":"0643D7","oi":1014920,"mp":0.0,"cp":0.0,"P":0,"F":0,"co":0.0,"L":50,"fl":"MM0"},{"n":"PJM N ILL HUB 5 OFF PEAK SWAP - NEW YORK MERCANTILE EXCHANGE","c":"064A79","oi":910105,"mp":-4.8,"cp":0.0,"P":0,"F":0,"co":0.0,"L":50,"fl":""},{"n":"AECO FIN BASIS - ICE FUTURES ENERGY DIV","c":"023396","oi":798830,"mp":0.9,"cp":-0.16,"P":0,"F":0,"co":0.0,"L":50,"fl":""},{"n":"AD HUB DA PEAK MONTHLY - ICE FUTURES ENERGY DIV","c":"06439F","oi":784200,"mp":0.0,"cp":0.0,"P":0,"F":0,"co":0.0,"L":50,"fl":"MM0"},{"n":"PJM JCPL ZONE DAY-AHEAD OFF-PEAK - ICE FUTURES ENERGY DIV","c":"0643CV","oi":754363,"mp":0.0,"cp":0.0,"P":0,"F":0,"co":0.0,"L":50,"fl":"MM0"},{"n":"NATURAL GAS PENULTIMATE ICE - ICE FUTURES ENERGY DIV","c":"023392","oi":713186,"mp":-3.8,"cp":-0.02,"P":0,"F":0,"co":0.0,"L":50,"fl":""},{"n":"PJM BGE ZONE DAY AHEAD OFF PEAK MONTHLY - ICE FUTURES ENERGY DIV","c":"0643CJ","oi":701198,"mp":-8.9,"cp":0.0,"P":0,"F":0,"co":0.0,"L":50,"fl":""},{"n":"PJM PEPCO DAY-AHEAD OFF-PEAK - ICE FUTURES ENERGY DIV","c":"0643D5","oi":627223,"mp":0.0,"cp":0.0,"P":0,"F":0,"co":0.0,"L":50,"fl":"MM0"},{"n":"PJM N ILL OFF PEAK DAY AHEAD - NEW YORK MERCANTILE EXCHANGE","c":"064A35","oi":627143,"mp":-0.7,"cp":0.0,"P":0,"F":0,"co":0.0,"L":50,"fl":""},{"n":"NORTHERN ILLINOIS HUB (REAL TIME LMP OFF-PEAK) - ICE FUTURES ENERGY DIV","c":"0643BS","oi":621425,"mp":1.5,"cp":0.13,"P":0,"F":0,"co":0.0,"L":50,"fl":""},{"n":"PSA-PJM PSEG ZONE DAY-AHEAD - ICE FUTURES ENERGY DIV","c":"0643DL","oi":603695,"mp":-0.1,"cp":0.0,"P":0,"F":0,"co":0.0,"L":50,"fl":""},{"n":"PJM WESTERN OFF PEAK DAY AHEAD - NEW YORK MERCANTILE EXCHANGE","c":"064A57","oi":596340,"mp":0.0,"cp":0.0,"P":0,"F":0,"co":0.0,"L":50,"fl":"MM0"},{"n":"NYISO ZONE G5 MW OFF PEAK SWAP - NEW YORK MERCANTILE EXCHANGE","c":"064A84","oi":587702,"mp":0.0,"cp":0.0,"P":0,"F":0,"co":0.0,"L":50,"fl":"MM0"},{"n":"AEP DAYTON HUB (REAL TIME LMP OFF-PEAK) - ICE FUTURES ENERGY DIV","c":"06439A","oi":554099,"mp":4.6,"cp":-0.22,"P":0,"F":0,"co":0.0,"L":50,"fl":""},{"n":"PJM PECO ZONE OFF-PEAK MONTHLY - ICE FUTURES ENERGY DIV","c":"0643D1","oi":502733,"mp":0.0,"cp":0.0,"P":0,"F":0,"co":0.0,"L":50,"fl":"MM0"},{"n":"MW CINRGY 5 OFF PEAK REAL-TIME - NEW YORK MERCANTILE EXCHANGE","c":"064A87","oi":436760,"mp":-1.4,"cp":0.0,"P":0,"F":0,"co":0.0,"L":50,"fl":""},{"n":"ISO NEW ENG HUB OFF PEAK SWAP - NEW YORK MERCANTILE EXCHANGE","c":"064A78","oi":391708,"mp":2.9,"cp":0.0,"P":0,"F":0,"co":0.0,"L":50,"fl":""},{"n":"N. ILLINOIS HUB DAY AHEAD LMP, PEAK MONTHLY - ICE FUTURES ENERGY DIV","c":"0643BE","oi":344755,"mp":0.6,"cp":0.0,"P":0,"F":0,"co":0.0,"L":50,"fl":""},{"n":"PJM PPL ZONE DAY AHEAD, PEAK MONTHLY - ICE FUTURES ENERGY DIV","c":"0643D8","oi":260855,"mp":0.0,"cp":0.0,"P":0,"F":0,"co":0.0,"L":50,"fl":"MM0"},{"n":"TEXAS EASTERN- M3 ZONE (DELIVERED) (BASIS) - ICE FUTURES ENERGY DIV","c":"0233CH","oi":231599,"mp":-1.1,"cp":0.27,"P":0,"F":0,"co":0.0,"L":50,"fl":""},{"n":"PJM JCPL ZONE DAY-AHEAD - ICE FUTURES ENERGY DIV","c":"0643CU","oi":225115,"mp":0.0,"cp":0.0,"P":0,"F":0,"co":0.0,"L":50,"fl":"MM0"},{"n":"PJM BGE ZONE DAY AHEAD, PEAK MONTHLY - ICE FUTURES ENERGY DIV","c":"0643CK","oi":213215,"mp":-2.5,"cp":0.0,"P":0,"F":0,"co":0.0,"L":50,"fl":""},{"n":"MISCO CINERGY HUB REAL TIME PEAK - ICE FUTURES ENERGY DIV","c":"0643B1","oi":208425,"mp":2.0,"cp":0.0,"P":0,"F":0,"co":0.0,"L":50,"fl":""},{"n":"NYISO ZONE  G  (OFF-PEAK) - ICE FUTURES ENERGY DIV","c":"0643C4","oi":195440,"mp":0.0,"cp":0.0,"P":0,"F":0,"co":0.0,"L":50,"fl":"MM0"},{"n":"PJM PEPCO DAY-AHEAD - ICE FUTURES ENERGY DIV","c":"0643D4","oi":193175,"mp":0.0,"cp":0.0,"P":0,"F":0,"co":0.0,"L":50,"fl":"MM0"},{"n":"ALGONQUIN CITY-GATES FINANCIAL BASIS - ICE FUTURES ENERGY DIV","c":"02339E","oi":168530,"mp":-10.8,"cp":-0.32,"P":10,"F":-10,"co":0.0,"L":50,"fl":""},{"n":"PALO VERDE (OFF-PEAK) - ICE FUTURES ENERGY DIV","c":"0643CC","oi":144505,"mp":0.0,"cp":0.0,"P":0,"F":0,"co":0.0,"L":50,"fl":"MM0"},{"n":"PJM PECO ZONE (DA LMP) PEAK MONTHLY - ICE FUTURES ENERGY DIV","c":"0643CZ","oi":139035,"mp":0.0,"cp":0.0,"P":0,"F":0,"co":0.0,"L":50,"fl":"MM0"},{"n":"EL PASO - PERMIAN BASIN (BASIS) - ICE FUTURES ENERGY DIV","c":"0233A5","oi":85493,"mp":-8.1,"cp":0.36,"P":0,"F":0,"co":0.0,"L":50,"fl":""},{"n":"COLUMBIA GULF TRANSMISSION CO. -  MAINLINE POOL - ICE FUTURES ENERGY DIV","c":"02339Y","oi":83092,"mp":0.0,"cp":0.07,"P":0,"F":0,"co":0.0,"L":50,"fl":"MM0"},{"n":"PJM WESTERN PEAK REAL TIME - NEW YORK MERCANTILE EXCHANGE","c":"064A58","oi":82154,"mp":4.5,"cp":0.0,"P":0,"F":0,"co":0.0,"L":50,"fl":""},{"n":"TRANSCONTINENTAL GAS- STATION 85 (ZONE 4) - ICE FUTURES ENERGY DIV","c":"0233CW","oi":79345,"mp":0.0,"cp":-0.46,"P":0,"F":0,"co":0.0,"L":50,"fl":"MM0"},{"n":"UP DOWN GC ULSD VS HO SPR SWAP - NEW YORK MERCANTILE EXCHANGE","c":"022A13","oi":76828,"mp":-2.1,"cp":0.0,"P":0,"F":0,"co":0.0,"L":50,"fl":""},{"n":"NORTHWEST PIPELINE - CANADIAN BORDER (BASIS) - ICE FUTURES ENERGY DIV","c":"0233BC","oi":62760,"mp":-3.4,"cp":0.0,"P":0,"F":0,"co":0.0,"L":50,"fl":"FLOW-NA"},{"n":"MID-C FINANCIAL PEAK - ICE FUTURES ENERGY DIV","c":"064391","oi":53671,"mp":3.0,"cp":-0.29,"P":0,"F":0,"co":0.0,"L":50,"fl":""},{"n":"NYISO ZONE G 5 MW PEAK SWAP - NEW YORK MERCANTILE EXCHANGE","c":"064A68","oi":51662,"mp":-0.8,"cp":0.0,"P":0,"F":0,"co":0.0,"L":50,"fl":""},{"n":"AEP DAYTON HUB (REAL TIME LMP) - ICE FUTURES ENERGY DIV","c":"06439B","oi":51056,"mp":2.1,"cp":0.45,"P":0,"F":0,"co":0.0,"L":50,"fl":""},{"n":"SP15 FIN DA PEAK FIXED - ICE FUTURES ENERGY DIV","c":"064395","oi":49544,"mp":-18.2,"cp":-1.24,"P":10,"F":-10,"co":0.0,"L":50,"fl":""},{"n":"GULF JET NY HEAT OIL SPR SWAP - NEW YORK MERCANTILE EXCHANGE","c":"86465A","oi":48531,"mp":0.0,"cp":-0.78,"P":0,"F":0,"co":0.0,"L":50,"fl":"MM0"},{"n":"TEXAS EASTERN- M3 ZONE (DELIVERED) - ICE FUTURES ENERGY DIV","c":"0233CG","oi":43658,"mp":-1.0,"cp":0.55,"P":0,"F":0,"co":0.0,"L":50,"fl":""},{"n":"PJM WESTERN PEAK DAY AHEAD - NEW YORK MERCANTILE EXCHANGE","c":"064A56","oi":42177,"mp":0.0,"cp":0.0,"P":0,"F":0,"co":0.0,"L":50,"fl":"MM0"},{"n":"PJM ELECTRICITY MONTHLY - NEW YORK MERCANTILE EXCHANGE","c":"064657","oi":36639,"mp":-5.1,"cp":0.88,"P":0,"F":0,"co":0.0,"L":50,"fl":""},{"n":"HOUSTON SHIP CHANNEL (INDEX) - ICE FUTURES ENERGY DIV","c":"0233AM","oi":34898,"mp":0.0,"cp":0.26,"P":0,"F":0,"co":0.0,"L":50,"fl":"MM0"},{"n":"COAL (API 4) FOB  RICH BAY FUT - NEW YORK MERCANTILE EXCHANGE","c":"024658","oi":34733,"mp":-14.7,"cp":-2.49,"P":10,"F":-10,"co":0.0,"L":50,"fl":""},{"n":"HENRY HUB PENULTIMATE FIN - NEW YORK MERCANTILE EXCHANGE","c":"023A56","oi":32712,"mp":0.2,"cp":0.0,"P":0,"F":0,"co":0.0,"L":50,"fl":"FLOW-NA"},{"n":"PJM N ILL PEAK DAY AHEAD - NEW YORK MERCANTILE EXCHANGE","c":"064A34","oi":29294,"mp":-1.2,"cp":0.0,"P":0,"F":0,"co":0.0,"L":50,"fl":""},{"n":"CHICAGO ETHANOL SWAP - NEW YORK MERCANTILE EXCHANGE","c":"025651","oi":27455,"mp":1.2,"cp":0.9,"P":0,"F":0,"co":0.0,"L":50,"fl":""},{"n":"EUROBOB OXY NWE CRK SPR - NEW YORK MERCANTILE EXCHANGE","c":"967654","oi":26508,"mp":4.7,"cp":1.02,"P":0,"F":0,"co":0.0,"L":50,"fl":""},{"n":"PALO VERDE - ICE FUTURES ENERGY DIV","c":"0643CB","oi":25415,"mp":-4.7,"cp":0.0,"P":0,"F":0,"co":0.0,"L":50,"fl":""},{"n":"MT BELVIEU PROPANE (OPIS) SWAP - NEW YORK MERCANTILE EXCHANGE","c":"06665O","oi":23886,"mp":0.0,"cp":0.15,"P":0,"F":0,"co":0.0,"L":50,"fl":"MM0"},{"n":"MISO CINERGY HUB (REAL-TIME LMP) - ICE FUTURES ENERGY DIV","c":"0643B3","oi":23869,"mp":5.3,"cp":-1.08,"P":0,"F":0,"co":0.0,"L":50,"fl":""},{"n":"MILK, Class III - CHICAGO MERCANTILE EXCHANGE","c":"052641","oi":22759,"mp":-1.9,"cp":0.27,"P":0,"F":0,"co":0.0,"L":50,"fl":""},{"n":"NYISO ZONE  A - ICE FUTURES ENERGY DIV","c":"0643BY","oi":21272,"mp":5.9,"cp":-0.36,"P":0,"F":0,"co":0.0,"L":50,"fl":""},{"n":"NYISO ZONE J 5 MW PEAK SWAP - NEW YORK MERCANTILE EXCHANGE","c":"064A69","oi":20857,"mp":0.0,"cp":0.0,"P":0,"F":0,"co":0.0,"L":50,"fl":"MM0|FLOW-NA"},{"n":"GULF COAST ULSD CRACK SPR SWAP - NEW YORK MERCANTILE EXCHANGE","c":"022A09","oi":20307,"mp":0.0,"cp":0.0,"P":0,"F":0,"co":0.0,"L":50,"fl":"MM0"},{"n":"NORTHWEST PIPELINE CORP. - ROCKY MOUNTAINS - ICE FUTURES ENERGY DIV","c":"0233BD","oi":19796,"mp":2.9,"cp":0.0,"P":0,"F":0,"co":0.0,"L":50,"fl":""},{"n":"DOMINION - SOUTH POINT - ICE FUTURES ENERGY DIV","c":"0233A2","oi":18208,"mp":1.4,"cp":0.0,"P":0,"F":0,"co":0.0,"L":50,"fl":"FLOW-NA"},{"n":"RBOB GASOLINE/BRENT CRACK SPRD - NEW YORK MERCANTILE EXCHANGE","c":"111A41","oi":16799,"mp":-1.5,"cp":0.61,"P":0,"F":0,"co":0.0,"L":50,"fl":""},{"n":"MT BELV NORM BUTANE OPIS SWAP - NEW YORK MERCANTILE EXCHANGE","c":"06665Q","oi":16381,"mp":0.0,"cp":0.15,"P":0,"F":0,"co":0.0,"L":50,"fl":"MM0"},{"n":"PJM AEP PEAK DAY AHEAD - NEW YORK MERCANTILE EXCHANGE","c":"064A38","oi":16209,"mp":0.0,"cp":-1.01,"P":0,"F":0,"co":0.0,"L":50,"fl":"MM0"},{"n":"NYISO ZONE  G - ICE FUTURES ENERGY DIV","c":"0643C3","oi":15920,"mp":-0.8,"cp":-1.34,"P":0,"F":0,"co":0.0,"L":50,"fl":""},{"n":"ERCOT - NORTH ZONE - ICE FUTURES ENERGY DIV","c":"06439R","oi":14479,"mp":9.2,"cp":-0.14,"P":0,"F":0,"co":0.0,"L":50,"fl":""},{"n":"HOT ROLLED COIL STEEL - NEW YORK MERCANTILE EXCHANGE","c":"192651","oi":14030,"mp":4.0,"cp":-1.03,"P":0,"F":0,"co":0.0,"L":50,"fl":""},{"n":"PJM CAL MONTH OFF PK LMP SWAP - NEW YORK MERCANTILE EXCHANGE","c":"06465M","oi":12816,"mp":-5.5,"cp":-0.41,"P":0,"F":0,"co":0.0,"L":50,"fl":""},{"n":"GRP 3 ULSD VS HEATING OIL SPR - NEW YORK MERCANTILE EXCHANGE","c":"022A60","oi":12600,"mp":0.0,"cp":0.0,"P":0,"F":0,"co":0.0,"L":50,"fl":"MM0"},{"n":"SING JET KERO GASOIL SPR SWAP - NEW YORK MERCANTILE EXCHANGE","c":"86465C","oi":12319,"mp":0.0,"cp":0.0,"P":0,"F":0,"co":0.0,"L":50,"fl":"MM0"},{"n":"NY RES FUEL 1.0% SULFUR SWAP - NEW YORK MERCANTILE EXCHANGE","c":"02165B","oi":11135,"mp":0.0,"cp":0.12,"P":0,"F":0,"co":0.0,"L":50,"fl":"MM0"},{"n":"NAPHTHA CRACK SPR SWAP - NEW YORK MERCANTILE EXCHANGE","c":"86665A","oi":10497,"mp":-0.2,"cp":-0.27,"P":0,"F":0,"co":0.0,"L":50,"fl":""},{"n":"RBOB UP-DOWN CAL SWAP - NEW YORK MERCANTILE EXCHANGE","c":"11165L","oi":10457,"mp":0.0,"cp":0.0,"P":0,"F":0,"co":0.0,"L":50,"fl":"MM0|FLOW-NA"},{"n":"ROUGH RICE - CHICAGO BOARD OF TRADE","c":"039601","oi":10329,"mp":-4.5,"cp":-1.1,"P":0,"F":0,"co":0.0,"L":50,"fl":""},{"n":"EUR 3.5% FUEL OIL RTD CAL SWAP - NEW YORK MERCANTILE EXCHANGE","c":"02165E","oi":10025,"mp":0.2,"cp":0.1,"P":0,"F":0,"co":0.0,"L":50,"fl":""},{"n":"SING JET KERO SWAP - NEW YORK MERCANTILE EXCHANGE","c":"26265D","oi":9985,"mp":0.0,"cp":-2.05,"P":0,"F":0,"co":0.0,"L":50,"fl":"MM0"},{"n":"MINI EUR 3.5%FOIL RTD CAL SWAP - NEW YORK MERCANTILE EXCHANGE","c":"021A17","oi":9777,"mp":0.0,"cp":-0.07,"P":0,"F":0,"co":0.0,"L":50,"fl":"MM0"},{"n":"CHEESE (CASH-SETTLED) - CHICAGO MERCANTILE EXCHANGE","c":"063642","oi":9193,"mp":0.0,"cp":-0.51,"P":0,"F":0,"co":0.0,"L":50,"fl":"MM0"},{"n":"MT BELV NAT GASOLINE OPIS SWAP - NEW YORK MERCANTILE EXCHANGE","c":"06665R","oi":7402,"mp":0.0,"cp":-1.08,"P":0,"F":0,"co":0.0,"L":50,"fl":"MM0"},{"n":"NY 1% V GULF 3% FUEL OIL SPR - NEW YORK MERCANTILE EXCHANGE","c":"02165T","oi":7314,"mp":0.0,"cp":0.82,"P":0,"F":0,"co":0.0,"L":50,"fl":"MM0"},{"n":"SING FUEL OIL 180 CAL SWAP - NEW YORK MERCANTILE EXCHANGE","c":"02165G","oi":7021,"mp":0.0,"cp":0.3,"P":0,"F":0,"co":0.0,"L":50,"fl":"MM0"},{"n":"NYISO  ZONE  J - ICE FUTURES ENERGY DIV","c":"0643BW","oi":6941,"mp":0.0,"cp":-0.62,"P":0,"F":0,"co":0.0,"L":50,"fl":"MM0"},{"n":"1% FUEL OIL NWE CRACK SPR - NEW YORK MERCANTILE EXCHANGE","c":"86565D","oi":6862,"mp":-6.3,"cp":0.0,"P":0,"F":0,"co":0.0,"L":50,"fl":""},{"n":"MINI SING 380 FUEL OIL SWAP - NEW YORK MERCANTILE EXCHANGE","c":"021A35","oi":5039,"mp":0.0,"cp":0.26,"P":0,"F":0,"co":0.0,"L":50,"fl":"MM0"},{"n":"RANDOM LENGTH LUMBER - CHICAGO MERCANTILE EXCHANGE","c":"058643","oi":4960,"mp":2.3,"cp":-6.03,"P":0,"F":0,"co":0.0,"L":50,"fl":""},{"n":"SING 380 FUEL OIL SWAP - NEW YORK MERCANTILE EXCHANGE","c":"02165K","oi":4900,"mp":0.0,"cp":-2.31,"P":0,"F":0,"co":0.0,"L":50,"fl":"MM0"},{"n":"BUTTER (CASH SETTLED) - CHICAGO MERCANTILE EXCHANGE","c":"050642","oi":4838,"mp":0.0,"cp":0.45,"P":0,"F":0,"co":0.0,"L":50,"fl":"MM0"},{"n":"CME MILK IV - CHICAGO MERCANTILE EXCHANGE","c":"052644","oi":4713,"mp":0.0,"cp":-2.06,"P":0,"F":0,"co":0.0,"L":50,"fl":"MM0"},{"n":"MINI SING FUELOIL 180 CAL SWAP - NEW YORK MERCANTILE EXCHANGE","c":"021A19","oi":4628,"mp":0.0,"cp":-0.84,"P":0,"F":0,"co":0.0,"L":50,"fl":"MM0"},{"n":"CBT ETHANOL - CHICAGO BOARD OF TRADE","c":"025601","oi":4536,"mp":2.5,"cp":-0.13,"P":0,"F":0,"co":0.0,"L":50,"fl":""},{"n":"Mini Eur Naphtha CIF NWE Swap - NEW YORK MERCANTILE EXCHANGE","c":"03265J","oi":3252,"mp":1.7,"cp":0.31,"P":0,"F":0,"co":0.0,"L":50,"fl":""},{"n":"SING 180 380 FUEL OIL SPR SWAP - NEW YORK MERCANTILE EXCHANGE","c":"02165J","oi":3071,"mp":0.0,"cp":0.0,"P":0,"F":0,"co":0.0,"L":50,"fl":"MM0|FLOW-NA"},{"n":"MINI JAPAN C&F NAPHTHA SWAP FU - NEW YORK MERCANTILE EXCHANGE","c":"86665E","oi":2441,"mp":0.0,"cp":2.46,"P":0,"F":0,"co":0.0,"L":50,"fl":"MM0"},{"n":"EUROPEAN NAPHTHA CAL SWAP - NEW YORK MERCANTILE EXCHANGE","c":"03265A","oi":2424,"mp":5.9,"cp":-0.08,"P":0,"F":0,"co":0.0,"L":50,"fl":""},{"n":"Nepool MH DA LMP Offpk Mon Min - ICE FUTURES ENERGY DIV","c":"0643B9","oi":2420761,"mp":1.3,"cp":1.98,"P":0,"F":10,"co":2.5,"L":51,"fl":""},{"n":"PJM WESTERN HUB REAL 50MW OFF - NEW YORK MERCANTILE EXCHANGE","c":"064A59","oi":1870269,"mp":-15.3,"cp":0.0,"P":10,"F":0,"co":2.5,"L":51,"fl":""},{"n":"CORN - CHICAGO BOARD OF TRADE","c":"002602","oi":1284218,"mp":-5.8,"cp":0.48,"P":0,"F":10,"co":2.5,"L":51,"fl":""},{"n":"CIN HUB DA OFF-PEAK - ICE FUTURES ENERGY DIV","c":"06439K","oi":912320,"mp":-0.4,"cp":0.44,"P":0,"F":10,"co":2.5,"L":51,"fl":""},{"n":"Nepool MH DA LMP Peak Mon Mini - ICE FUTURES ENERGY DIV","c":"0643BA","oi":784825,"mp":-5.6,"cp":0.37,"P":0,"F":10,"co":2.5,"L":51,"fl":""},{"n":"MID-C FINANCIAL OFF-PEAK - ICE FUTURES ENERGY DIV","c":"064392","oi":480036,"mp":0.9,"cp":0.86,"P":0,"F":10,"co":2.5,"L":51,"fl":""},{"n":"HENRY HUB LAST DAY FIN - NEW YORK MERCANTILE EXCHANGE","c":"023A55","oi":413465,"mp":9.8,"cp":0.71,"P":0,"F":10,"co":2.5,"L":51,"fl":""},{"n":"MISCO CINERGY DAY AHEAD LMP, PEAK MONTHLY - ICE FUTURES ENERGY DIV","c":"0643AZ","oi":332195,"mp":0.6,"cp":0.6,"P":0,"F":10,"co":2.5,"L":51,"fl":""},{"n":"PANHANDLE EASTERN- POOL GAS (BASIS) - ICE FUTURES ENERGY DIV","c":"0233BL","oi":300947,"mp":-1.8,"cp":1.64,"P":0,"F":10,"co":2.5,"L":51,"fl":""},{"n":"NO. 2 HEATING OIL, N.Y. HARBOR - NEW YORK MERCANTILE EXCHANGE","c":"022651","oi":283846,"mp":5.0,"cp":0.49,"P":0,"F":10,"co":2.5,"L":51,"fl":""},{"n":"CHICAGO FIN BASIS - ICE FUTURES ENERGY DIV","c":"023397","oi":240782,"mp":-0.3,"cp":0.74,"P":0,"F":10,"co":2.5,"L":51,"fl":""},{"n":"PJM WH REAL TIME PEAK - ICE FUTURES ENERGY DIV","c":"064363","oi":163080,"mp":7.1,"cp":0.84,"P":0,"F":10,"co":2.5,"L":51,"fl":""},{"n":"PJM N ILL HUB 5 MW PEAK SWAP - NEW YORK MERCANTILE EXCHANGE","c":"064A63","oi":56804,"mp":-13.5,"cp":0.0,"P":10,"F":0,"co":2.5,"L":51,"fl":""},{"n":"ISO NEW ENG INT HUB PEAK SWAP - NEW YORK MERCANTILE EXCHANGE","c":"064A60","oi":25254,"mp":-15.6,"cp":0.0,"P":10,"F":0,"co":2.5,"L":51,"fl":""},{"n":"RBOB CALENDAR SWAP - NEW YORK MERCANTILE EXCHANGE","c":"11165K","oi":14483,"mp":-10.7,"cp":-1.32,"P":10,"F":0,"co":2.5,"L":51,"fl":""},{"n":"HSC FIN BASIS - ICE FUTURES ENERGY DIV","c":"023398","oi":258498,"mp":1.6,"cp":2.53,"P":0,"F":20,"co":5.0,"L":53,"fl":""},{"n":"NWP ROCKIES FIN BASIS - ICE FUTURES ENERGY DIV","c":"023395","oi":232930,"mp":-0.7,"cp":1.95,"P":0,"F":20,"co":5.0,"L":53,"fl":""},{"n":"COTTON NO. 2 - ICE FUTURES U.S.","c":"033661","oi":202364,"mp":18.0,"cp":4.44,"P":-10,"F":30,"co":5.0,"L":53,"fl":""},{"n":"COLUMBIA GAS CO. - TCO POOL (APPALACHIA) (BASIS) - ICE FUTURES ENERGY DIV","c":"02339W","oi":156678,"mp":1.1,"cp":0.6,"P":0,"F":20,"co":5.0,"L":53,"fl":""},{"n":"BRENT CRUDE OIL LAST DAY - NEW YORK MERCANTILE EXCHANGE","c":"06765T","oi":61439,"mp":-4.8,"cp":3.06,"P":0,"F":20,"co":5.0,"L":53,"fl":""},{"n":"3.5% FUEL OIL RDAM CRACK SPR - NEW YORK MERCANTILE EXCHANGE","c":"86565C","oi":36672,"mp":-10.2,"cp":1.99,"P":10,"F":10,"co":5.0,"L":53,"fl":""},{"n":"SOCAL (INDEX) - ICE FUTURES ENERGY DIV","c":"0233BW","oi":34680,"mp":-1.6,"cp":2.51,"P":0,"F":20,"co":5.0,"L":53,"fl":""},{"n":"GULF NO6 FO 3% v EUR 3.5% RDAM - NEW YORK MERCANTILE EXCHANGE","c":"021A28","oi":27476,"mp":0.0,"cp":3.91,"P":0,"F":20,"co":5.0,"L":53,"fl":"MM0"},{"n":"SP15 FIN DA LPM OFF-PEAK - ICE FUTURES ENERGY DIV","c":"064396","oi":325886,"mp":-14.2,"cp":2.67,"P":10,"F":20,"co":7.5,"L":54,"fl":""},{"n":"PG&E CITYGATE FIN BASIS - ICE FUTURES ENERGY DIV","c":"023394","oi":170286,"mp":1.6,"cp":2.71,"P":0,"F":30,"co":7.5,"L":54,"fl":""},{"n":"COFFEE C - ICE FUTURES U.S.","c":"083731","oi":160516,"mp":-15.0,"cp":2.71,"P":10,"F":20,"co":7.5,"L":54,"fl":""},{"n":"MICHIGAN CONSOLIDATED CITYGATE (GENERIC) (BASIS) - ICE FUTURES ENERGY DIV","c":"0233AQ","oi":131165,"mp":0.0,"cp":2.76,"P":0,"F":30,"co":7.5,"L":54,"fl":"MM0"},{"n":"NATURAL GAS PIPELINE, TEXOK (BASIS) - ICE FUTURES ENERGY DIV","c":"0233B1","oi":116033,"mp":-0.9,"cp":3.88,"P":0,"F":30,"co":7.5,"L":54,"fl":""},{"n":"TRANSCO ZONE 6 BASIS - ICE FUTURES ENERGY DIV","c":"0233CU","oi":68833,"mp":9.5,"cp":4.26,"P":0,"F":40,"co":10.0,"L":55,"fl":""},{"n":"FRZN CONCENTRATED ORANGE JUICE - ICE FUTURES U.S.","c":"040701","oi":16343,"mp":-14.7,"cp":13.38,"P":10,"F":40,"co":12.5,"L":56,"fl":""}]}