{"date":"2018-11-13","rows":[{"n":"BLACK SEA WHEAT FINANCIAL - CHICAGO BOARD OF TRADE","c":"00160F","oi":19870,"mp":26.0,"cp":-5.21,"P":-20,"F":-30,"co":-12.5,"L":44,"fl":""},{"n":"HHUB NAT GAS PENULT FINL-2500 - NASDAQ FUTURES","c":"023P03","oi":93239,"mp":-3.7,"cp":-7.2,"P":0,"F":-30,"co":-7.5,"L":46,"fl":""},{"n":"CHICAGO ETHANOL - NEW YORK MERCANTILE EXCHANGE","c":"025651","oi":46742,"mp":13.9,"cp":-1.29,"P":-10,"F":-20,"co":-7.5,"L":46,"fl":""},{"n":"PJM.PSEG_month_off_dap - NODAL EXCHANGE","c":"064EXF","oi":42950,"mp":37.5,"cp":-1.22,"P":-20,"F":-10,"co":-7.5,"L":46,"fl":""},{"n":"PALLADIUM - NEW YORK MERCANTILE EXCHANGE","c":"075651","oi":27460,"mp":45.7,"cp":0.03,"P":-30,"F":0,"co":-7.5,"L":46,"fl":""},{"n":"PJM.N ILLINOIS HUB_month_on_rtp - NODAL EXCHANGE","c":"064FKC","oi":22045,"mp":40.7,"cp":-0.68,"P":-30,"F":0,"co":-7.5,"L":46,"fl":""},{"n":"ARGUS MARS vs WTI TRADE MONTH - ICE FUTURES ENERGY DIV","c":"06742R","oi":10955,"mp":0.0,"cp":-7.99,"P":0,"F":-30,"co":-7.5,"L":46,"fl":"MM0"},{"n":"NATURAL GAS HENRY LD1 FIXED - ICE FUTURES ENERGY DIV","c":"023391","oi":5404603,"mp":2.4,"cp":-2.61,"P":0,"F":-20,"co":-5.0,"L":48,"fl":""},{"n":"NATURAL GAS - NEW YORK MERCANTILE EXCHANGE","c":"023651","oi":1520152,"mp":18.4,"cp":-0.99,"P":-10,"F":-10,"co":-5.0,"L":48,"fl":""},{"n":"COLORADO INTERSTATE - MAINLINE (BASIS) - ICE FUTURES ENERGY DIV","c":"02339U","oi":248057,"mp":0.4,"cp":-1.45,"P":0,"F":-20,"co":-5.0,"L":48,"fl":""},{"n":"EL PASO - PERMIAN BASIN (BASIS) - ICE FUTURES ENERGY DIV","c":"0233A5","oi":216848,"mp":-1.6,"cp":-1.57,"P":0,"F":-20,"co":-5.0,"L":48,"fl":""},{"n":"ARGUS WTI Mid/WTI TRADE MONTH - ICE FUTURES ENERGY DIV","c":"06742U","oi":213654,"mp":0.0,"cp":-0.95,"P":0,"F":-20,"co":-5.0,"L":48,"fl":"MM0"},{"n":"BRENT CRUDE OIL LAST DAY - NEW YORK MERCANTILE EXCHANGE","c":"06765T","oi":207728,"mp":0.4,"cp":-2.35,"P":0,"F":-20,"co":-5.0,"L":48,"fl":""},{"n":"WTI CRUDE OIL CALENDAR SWAP - NEW YORK MERCANTILE EXCHANGE","c":"06765A","oi":167571,"mp":0.0,"cp":-1.14,"P":0,"F":-20,"co":-5.0,"L":48,"fl":"MM0"},{"n":"NATURAL GAS PENULTIMATE ICE - ICE FUTURES ENERGY DIV","c":"023392","oi":144951,"mp":-23.0,"cp":-5.53,"P":10,"F":-30,"co":-5.0,"L":48,"fl":""},{"n":"PJM.WESTERN HUB_month_on_dap - NODAL EXCHANGE","c":"064FHK","oi":112334,"mp":5.6,"cp":-2.81,"P":0,"F":-20,"co":-5.0,"L":48,"fl":""},{"n":"PJM.WESTERN HUB_month_off_dap - NODAL EXCHANGE","c":"064FHL","oi":105483,"mp":7.8,"cp":-3.28,"P":0,"F":-20,"co":-5.0,"L":48,"fl":""},{"n":"WHEAT-HRSpring - MINNEAPOLIS GRAIN EXCHANGE","c":"001626","oi":76839,"mp":-7.6,"cp":-1.48,"P":0,"F":-20,"co":-5.0,"L":48,"fl":""},{"n":"PJM N. IL HUB RT PEAK - ICE FUTURES ENERGY DIV","c":"0643BT","oi":57718,"mp":35.8,"cp":-0.27,"P":-20,"F":0,"co":-5.0,"L":48,"fl":""},{"n":"PJM.PSEG_month_on_dap - NODAL EXCHANGE","c":"064EXE","oi":45370,"mp":35.4,"cp":-1.02,"P":-20,"F":0,"co":-5.0,"L":48,"fl":""},{"n":"CRUDE DIFF-TMX WCS 1A INDEX - ICE FUTURES ENERGY DIV","c":"06742G","oi":33653,"mp":0.0,"cp":-2.12,"P":0,"F":-20,"co":-5.0,"L":48,"fl":"MM0"},{"n":"PJM.N ILLINOIS HUB_month_on_dap - NODAL EXCHANGE","c":"064ERM","oi":27324,"mp":33.4,"cp":-0.73,"P":-20,"F":0,"co":-5.0,"L":48,"fl":""},{"n":"HOT ROLLED COIL STEEL - NEW YORK MERCANTILE EXCHANGE","c":"192651","oi":17080,"mp":5.0,"cp":-2.93,"P":0,"F":-20,"co":-5.0,"L":48,"fl":""},{"n":"HENRY HUB - NEW YORK MERCANTILE EXCHANGE","c":"03565B","oi":1059627,"mp":2.6,"cp":-2.15,"P":0,"F":-10,"co":-2.5,"L":49,"fl":""},{"n":"WHEAT-SRW - CHICAGO BOARD OF TRADE","c":"001602","oi":493814,"mp":-5.8,"cp":-1.88,"P":0,"F":-10,"co":-2.5,"L":49,"fl":""},{"n":"WAHA FIN BASIS - ICE FUTURES ENERGY DIV","c":"023399","oi":298710,"mp":-0.0,"cp":-1.04,"P":0,"F":-10,"co":-2.5,"L":49,"fl":""},{"n":"COCOA - ICE FUTURES U.S.","c":"073732","oi":239006,"mp":-5.4,"cp":-0.98,"P":0,"F":-10,"co":-2.5,"L":49,"fl":""},{"n":"HENRY HUB - TAILGATE LOUISIANA (BASIS) - ICE FUTURES ENERGY DIV","c":"0233AG","oi":192106,"mp":0.0,"cp":-0.43,"P":0,"F":-10,"co":-2.5,"L":49,"fl":"MM0"},{"n":"PACIFIC GAS TRANSMISSION - MALIN (BASIS) - ICE FUTURES ENERGY DIV","c":"0233BH","oi":179877,"mp":-0.0,"cp":-0.55,"P":0,"F":-10,"co":-2.5,"L":49,"fl":""},{"n":"COLUMBIA GAS CO. - TCO POOL (APPALACHIA) (BASIS) - ICE FUTURES ENERGY DIV","c":"02339W","oi":155526,"mp":-1.4,"cp":-0.45,"P":0,"F":-10,"co":-2.5,"L":49,"fl":""},{"n":"PJM WESTERN HUB RT OFF - ICE FUTURES ENERGY DIV","c":"064394","oi":154837,"mp":-2.3,"cp":-0.44,"P":0,"F":-10,"co":-2.5,"L":49,"fl":""},{"n":"PJM WESTERN HUB DA PEAK - ICE FUTURES ENERGY DIV","c":"0643DC","oi":127259,"mp":-0.1,"cp":-0.87,"P":0,"F":-10,"co":-2.5,"L":49,"fl":""},{"n":"MT BELVIEU LDH PROPANE (OPIS) - NEW YORK MERCANTILE EXCHANGE","c":"06665O","oi":122425,"mp":2.6,"cp":-0.43,"P":0,"F":-10,"co":-2.5,"L":49,"fl":""},{"n":"ISO NE MASS HUB DA PEAK - ICE FUTURES ENERGY DIV","c":"0643BG","oi":116726,"mp":-0.4,"cp":-0.77,"P":0,"F":-10,"co":-2.5,"L":49,"fl":""},{"n":"PJM WESTERN HUB DA OFF-PK - ICE FUTURES ENERGY DIV","c":"0643DB","oi":112341,"mp":0.8,"cp":-0.79,"P":0,"F":-10,"co":-2.5,"L":49,"fl":""},{"n":"PJM AEP DAYTON RT PEAK FIXED - ICE FUTURES ENERGY DIV","c":"06439B","oi":71392,"mp":13.4,"cp":-0.34,"P":-10,"F":0,"co":-2.5,"L":49,"fl":""},{"n":"PJM.AEP-DAYTON HUB_month_off_dap - NODAL EXCHANGE","c":"064DLX","oi":67103,"mp":1.8,"cp":-0.77,"P":0,"F":-10,"co":-2.5,"L":49,"fl":""},{"n":"CALIF CARBON ALL VINTAGE 2018 - ICE FUTURES ENERGY DIV","c":"0063A2","oi":60199,"mp":6.6,"cp":-1.13,"P":0,"F":-10,"co":-2.5,"L":49,"fl":"ENV"},{"n":"EUROBOB OXY NWE CRK SPR  - NEW YORK MERCANTILE EXCHANGE","c":"967654","oi":30800,"mp":19.4,"cp":-0.01,"P":-10,"F":0,"co":-2.5,"L":49,"fl":""},{"n":"PJM WH REAL TIME PEAK - ICE FUTURES ENERGY DIV","c":"064363","oi":28536,"mp":22.5,"cp":-0.15,"P":-10,"F":0,"co":-2.5,"L":49,"fl":""},{"n":"PALO VERDE DA PEAK - ICE FUTURES ENERGY DIV","c":"0643CB","oi":21351,"mp":11.1,"cp":0.85,"P":-10,"F":0,"co":-2.5,"L":49,"fl":""},{"n":"CALIF CARBON ALL VINTAGE 2019 - ICE FUTURES ENERGY DIV","c":"0063AS","oi":19373,"mp":18.1,"cp":-1.55,"P":-10,"F":0,"co":-2.5,"L":49,"fl":"ENV"},{"n":"DOMINION - SOUTH POINT - ICE FUTURES ENERGY DIV","c":"0233A2","oi":16780,"mp":10.0,"cp":0.0,"P":-10,"F":0,"co":-2.5,"L":49,"fl":""},{"n":"OATS - CHICAGO BOARD OF TRADE","c":"004603","oi":6688,"mp":17.4,"cp":-2.3,"P":-10,"F":0,"co":-2.5,"L":49,"fl":""},{"n":"AECO FIN BASIS - ICE FUTURES ENERGY DIV","c":"023396","oi":829712,"mp":0.0,"cp":-0.12,"P":0,"F":0,"co":0.0,"L":50,"fl":"MM0"},{"n":"DOMINION - SOUTH POINT (BASIS) - ICE FUTURES ENERGY DIV","c":"0233A3","oi":555246,"mp":0.7,"cp":0.02,"P":0,"F":0,"co":0.0,"L":50,"fl":""},{"n":"HENRY HUB LAST DAY FIN - NEW YORK MERCANTILE EXCHANGE","c":"023A55","oi":480736,"mp":1.0,"cp":-0.27,"P":0,"F":0,"co":0.0,"L":50,"fl":""},{"n":"GASOLINE BLENDSTOCK (RBOB)  - NEW YORK MERCANTILE EXCHANGE","c":"111659","oi":419830,"mp":12.5,"cp":1.88,"P":-10,"F":10,"co":0.0,"L":50,"fl":""},{"n":"CHICAGO FIN BASIS - ICE FUTURES ENERGY DIV","c":"023397","oi":414005,"mp":-0.2,"cp":0.06,"P":0,"F":0,"co":0.0,"L":50,"fl":""},{"n":"LIVE CATTLE - CHICAGO MERCANTILE EXCHANGE","c":"057642","oi":337792,"mp":15.2,"cp":2.12,"P":-10,"F":10,"co":0.0,"L":50,"fl":""},{"n":"SOCAL BORDER FIN BASIS - ICE FUTURES ENERGY DIV","c":"023393","oi":269496,"mp":-1.9,"cp":0.23,"P":0,"F":0,"co":0.0,"L":50,"fl":""},{"n":"MICHIGAN CONSOLIDATED CITYGATE (GENERIC) (BASIS) - ICE FUTURES ENERGY DIV","c":"0233AQ","oi":269130,"mp":0.0,"cp":-0.07,"P":0,"F":0,"co":0.0,"L":50,"fl":"MM0"},{"n":"PJM WESTERN HUB RT PEAK MINI - ICE FUTURES ENERGY DIV","c":"0643DF","oi":256519,"mp":-3.0,"cp":-0.17,"P":0,"F":0,"co":0.0,"L":50,"fl":""},{"n":"COLUMBIA GULF TRANSMISSION CO. -  MAINLINE POOL - ICE FUTURES ENERGY DIV","c":"02339Y","oi":242389,"mp":0.0,"cp":-0.24,"P":0,"F":0,"co":0.0,"L":50,"fl":"MM0"},{"n":"LEAN HOGS - CHICAGO MERCANTILE EXCHANGE","c":"054642","oi":241054,"mp":12.2,"cp":0.39,"P":-10,"F":10,"co":0.0,"L":50,"fl":""},{"n":"TEXAS EASTERN- M3 ZONE (DELIVERED) (BASIS) - ICE FUTURES ENERGY DIV","c":"0233CH","oi":234238,"mp":-0.8,"cp":-0.19,"P":0,"F":0,"co":0.0,"L":50,"fl":""},{"n":"TETCO M2 Basis (Receipts) - ICE FUTURES ENERGY DIV","c":"0233DR","oi":211266,"mp":0.0,"cp":-0.01,"P":0,"F":0,"co":0.0,"L":50,"fl":"MM0"},{"n":"NATURAL GAS PIPELINE-TEXOK (BASIS) - ICE FUTURES ENERGY DIV","c":"0233B1","oi":204115,"mp":0.5,"cp":-0.21,"P":0,"F":0,"co":0.0,"L":50,"fl":""},{"n":"NORTHERN NATURAL GAS - VENTURA (BASIS) - ICE FUTURES ENERGY DIV","c":"0233BB","oi":201863,"mp":0.0,"cp":0.23,"P":0,"F":0,"co":0.0,"L":50,"fl":"MM0"},{"n":"HENRY HUB - TAILGATE LOUISIANA (INDEX) - ICE FUTURES ENERGY DIV","c":"0233AH","oi":199094,"mp":-5.3,"cp":0.05,"P":0,"F":0,"co":0.0,"L":50,"fl":""},{"n":"REX ZONE 3 BASIS - ICE FUTURES ENERGY DIV","c":"0233EB","oi":188740,"mp":0.0,"cp":-0.11,"P":0,"F":0,"co":0.0,"L":50,"fl":"MM0"},{"n":"PANHANDLE EASTERN- POOL GAS (BASIS) - ICE FUTURES ENERGY DIV","c":"0233BL","oi":159330,"mp":0.0,"cp":-0.23,"P":0,"F":0,"co":0.0,"L":50,"fl":"MM0"},{"n":"WTI MIDLAND ARGUS VS WTI TRADE - NEW YORK MERCANTILE EXCHANGE","c":"067A71","oi":154417,"mp":0.0,"cp":0.2,"P":0,"F":0,"co":0.0,"L":50,"fl":"MM0"},{"n":"TRANSCO ZONE 6 BASIS - ICE FUTURES ENERGY DIV","c":"0233CU","oi":153700,"mp":-0.1,"cp":-0.27,"P":0,"F":0,"co":0.0,"L":50,"fl":""},{"n":"WTI-BRENT CALENDAR SWAP - NEW YORK MERCANTILE EXCHANGE","c":"06765L","oi":133977,"mp":5.2,"cp":1.13,"P":0,"F":0,"co":0.0,"L":50,"fl":""},{"n":"TRANSCONTINENTAL GAS- STATION 85 (ZONE 4) - ICE FUTURES ENERGY DIV","c":"0233CW","oi":131306,"mp":0.0,"cp":0.08,"P":0,"F":0,"co":0.0,"L":50,"fl":"MM0"},{"n":"NATURAL GAS PIPELINE-MID-CONTINENT POOL PIN (BASIS) - ICE FUTURES ENERGY DIV","c":"0233AY","oi":117940,"mp":0.1,"cp":0.06,"P":0,"F":0,"co":0.0,"L":50,"fl":""},{"n":"TRANSCO LEIDY BASIS - ICE FUTURES ENERGY DIV","c":"0233DT","oi":112475,"mp":-0.8,"cp":-0.11,"P":0,"F":0,"co":0.0,"L":50,"fl":""},{"n":"PJM AEP DAYTON DA PEAK - ICE FUTURES ENERGY DIV","c":"06439F","oi":111784,"mp":1.1,"cp":-0.32,"P":0,"F":0,"co":0.0,"L":50,"fl":""},{"n":"ALGONQUIN CITY-GATES FINANCIAL BASIS - ICE FUTURES ENERGY DIV","c":"02339E","oi":107374,"mp":0.0,"cp":0.07,"P":0,"F":0,"co":0.0,"L":50,"fl":"MM0"},{"n":"NORTHWEST PIPELINE - CANADIAN BORDER (BASIS) - ICE FUTURES ENERGY DIV","c":"0233BC","oi":81785,"mp":0.0,"cp":0.3,"P":0,"F":0,"co":0.0,"L":50,"fl":"MM0"},{"n":"PJM AEP DAYTON HUB DA OFF-PK  - ICE FUTURES ENERGY DIV","c":"06439C","oi":78724,"mp":0.8,"cp":-0.08,"P":0,"F":0,"co":0.0,"L":50,"fl":""},{"n":"PJM N. IL HUB DA PEAK - ICE FUTURES ENERGY DIV","c":"0643BE","oi":73442,"mp":1.6,"cp":-0.49,"P":0,"F":0,"co":0.0,"L":50,"fl":""},{"n":"EL PASO-SAN JUAN BASIN-BLANCO POOL PRIMARY ONLY-BASIS - ICE FUTURES ENERGY DIV","c":"0233A8","oi":70129,"mp":0.0,"cp":0.18,"P":0,"F":0,"co":0.0,"L":50,"fl":"MM0"},{"n":"PJM.AEP-DAYTON HUB_month_on_dap - NODAL EXCHANGE","c":"064DLW","oi":68721,"mp":0.1,"cp":-0.46,"P":0,"F":0,"co":0.0,"L":50,"fl":""},{"n":"PJM N. IL HUB DA OFF-PK  - ICE FUTURES ENERGY DIV","c":"0643BC","oi":67660,"mp":1.3,"cp":-0.59,"P":0,"F":0,"co":0.0,"L":50,"fl":""},{"n":"HHUB NAT GAS PENULT FINL-10000 - NASDAQ FUTURES","c":"023P02","oi":64522,"mp":10.7,"cp":1.54,"P":-10,"F":10,"co":0.0,"L":50,"fl":""},{"n":"PROPANE OPIS MT BELVIEU TET FP - ICE FUTURES ENERGY DIV","c":"06641G","oi":64173,"mp":0.1,"cp":0.16,"P":0,"F":0,"co":0.0,"L":50,"fl":""},{"n":"TRANSCONTINENTAL GAS - ZONE 6 (NY) (BASIS) - ICE FUTURES ENERGY DIV","c":"0233CZ","oi":62497,"mp":0.8,"cp":-0.38,"P":0,"F":0,"co":0.0,"L":50,"fl":""},{"n":"PROPANE NON-LDH MT BEL SWAP - NEW YORK MERCANTILE EXCHANGE","c":"06665G","oi":55718,"mp":0.0,"cp":0.13,"P":0,"F":0,"co":0.0,"L":50,"fl":"MM0"},{"n":"MISO IN. DAY-AHEAD PEAK - ICE FUTURES ENERGY DIV","c":"0643AZ","oi":52888,"mp":0.5,"cp":0.13,"P":0,"F":0,"co":0.0,"L":50,"fl":""},{"n":"ERCOT NORTH 345KV RT PK FIX - ICE FUTURES ENERGY DIV","c":"06439R","oi":52821,"mp":5.0,"cp":0.06,"P":0,"F":0,"co":0.0,"L":50,"fl":""},{"n":"PJM PPL ZONE DAY AHEAD, OFF-PEAK MONTHLY - ICE FUTURES ENERGY DIV","c":"0643D7","oi":51989,"mp":0.6,"cp":0.04,"P":0,"F":0,"co":0.0,"L":50,"fl":""},{"n":"PJM PPL ZONE DA PEAK - ICE FUTURES ENERGY DIV","c":"0643D8","oi":51516,"mp":0.6,"cp":0.63,"P":0,"F":0,"co":0.0,"L":50,"fl":""},{"n":"PJM NI HUB RT OFF-PK - ICE FUTURES ENERGY DIV","c":"0643BS","oi":50758,"mp":0.2,"cp":0.0,"P":0,"F":0,"co":0.0,"L":50,"fl":""},{"n":"CAISO NP-15 PEAK - ICE FUTURES ENERGY DIV","c":"0643BM","oi":48710,"mp":-0.2,"cp":0.31,"P":0,"F":0,"co":0.0,"L":50,"fl":""},{"n":"WAHA HUB - WEST TEXAS DELIVERED/BUYER'S INDEX - ICE FUTURES ENERGY DIV","c":"0233D4","oi":48381,"mp":0.0,"cp":-0.38,"P":0,"F":0,"co":0.0,"L":50,"fl":"MM0"},{"n":"MT BELV NORM BUTANE OPIS - NEW YORK MERCANTILE EXCHANGE","c":"06665Q","oi":47751,"mp":1.1,"cp":0.73,"P":0,"F":0,"co":0.0,"L":50,"fl":""},{"n":"PJM.PPL_month_on_dap - NODAL EXCHANGE","c":"064EWU","oi":46490,"mp":-16.5,"cp":-1.56,"P":10,"F":-10,"co":0.0,"L":50,"fl":""},{"n":"PJM AEP DAYTON RT OFF-PK - ICE FUTURES ENERGY DIV","c":"06439A","oi":46286,"mp":0.9,"cp":0.49,"P":0,"F":0,"co":0.0,"L":50,"fl":""},{"n":"PJM.PPL_month_off_dap - NODAL EXCHANGE","c":"064EWV","oi":45680,"mp":-17.9,"cp":-1.42,"P":10,"F":-10,"co":0.0,"L":50,"fl":""},{"n":"NYISO ZONE G DA PEAK - ICE FUTURES ENERGY DIV","c":"0643C3","oi":45097,"mp":-2.4,"cp":0.07,"P":0,"F":0,"co":0.0,"L":50,"fl":""},{"n":"PJM.WESTERN HUB_month_off_rtp - NODAL EXCHANGE","c":"064FKF","oi":44650,"mp":-9.8,"cp":-0.34,"P":0,"F":0,"co":0.0,"L":50,"fl":""},{"n":"NJ SRECS VINTAGE 2020 - ICE FUTURES ENERGY DIV","c":"0063A4","oi":43666,"mp":0.0,"cp":0.23,"P":0,"F":0,"co":0.0,"L":50,"fl":"ENV|MM0"},{"n":"TEXAS EASTERN- M3 ZONE (DELIVERED) - ICE FUTURES ENERGY DIV","c":"0233CG","oi":43516,"mp":0.0,"cp":0.0,"P":0,"F":0,"co":0.0,"L":50,"fl":"MM0"},{"n":"MISO INDIANA HUB RT PEAK - ICE FUTURES ENERGY DIV","c":"0643B3","oi":42773,"mp":3.9,"cp":0.94,"P":0,"F":0,"co":0.0,"L":50,"fl":""},{"n":"RGGI VINTAGE 2018 - ICE FUTURES ENERGY DIV","c":"0063CD","oi":42728,"mp":0.0,"cp":0.0,"P":0,"F":0,"co":0.0,"L":50,"fl":"ENV|MM0"},{"n":"CHICAGO CITYGATE (INDEX) - ICE FUTURES ENERGY DIV","c":"02339Q","oi":42149,"mp":0.0,"cp":-0.72,"P":0,"F":0,"co":0.0,"L":50,"fl":"MM0"},{"n":"NJ SRECS VINTAGE 2019 - ICE FUTURES ENERGY DIV","c":"0063A3","oi":42145,"mp":0.0,"cp":-0.83,"P":0,"F":0,"co":0.0,"L":50,"fl":"ENV|MM0"},{"n":"MID-C DAY-AHEAD PEAK - ICE FUTURES ENERGY DIV","c":"064391","oi":42057,"mp":-1.5,"cp":-0.25,"P":0,"F":0,"co":0.0,"L":50,"fl":""},{"n":"MISO INDIANA  OFF-PEAK - ICE FUTURES ENERGY DIV","c":"06439K","oi":40625,"mp":0.8,"cp":0.25,"P":0,"F":0,"co":0.0,"L":50,"fl":""},{"n":"NYISO ZONE G DA OFF-PK - ICE FUTURES ENERGY DIV","c":"0643C4","oi":39352,"mp":3.1,"cp":0.01,"P":0,"F":0,"co":0.0,"L":50,"fl":""},{"n":"UP DOWN GC ULSD VS HO SPR - NEW YORK MERCANTILE EXCHANGE","c":"022A13","oi":39254,"mp":0.0,"cp":0.54,"P":0,"F":0,"co":0.0,"L":50,"fl":"MM0"},{"n":"MT BELVIEU ETHANE OPIS - NEW YORK MERCANTILE EXCHANGE","c":"06665P","oi":39014,"mp":2.6,"cp":-0.31,"P":0,"F":0,"co":0.0,"L":50,"fl":""},{"n":"ETHANE, MT. BELV-ENTERPRISE - ICE FUTURES ENERGY DIV","c":"066416","oi":36417,"mp":0.0,"cp":0.03,"P":0,"F":0,"co":0.0,"L":50,"fl":"MM0"},{"n":"NYISO ZONE J DA PEAK - ICE FUTURES ENERGY DIV","c":"0643BW","oi":35573,"mp":0.5,"cp":-0.51,"P":0,"F":0,"co":0.0,"L":50,"fl":""},{"n":"NORTHWEST PIPELINE CORP. - ROCKY MOUNTAINS - ICE FUTURES ENERGY DIV","c":"0233BD","oi":34108,"mp":0.9,"cp":0.0,"P":0,"F":0,"co":0.0,"L":50,"fl":"FLOW-NA"},{"n":"NYISO ZONE A DA PEAK - ICE FUTURES ENERGY DIV","c":"0643BY","oi":34106,"mp":-2.2,"cp":-0.1,"P":0,"F":0,"co":0.0,"L":50,"fl":""},{"n":"GULF # 6 FUEL 3.0% SULFUR SWAP - NEW YORK MERCANTILE EXCHANGE","c":"02165A","oi":33911,"mp":-0.5,"cp":-1.14,"P":0,"F":0,"co":0.0,"L":50,"fl":""},{"n":"PJM TRI-RECs CLASS 1 Vin 2020 - ICE FUTURES ENERGY DIV","c":"0063AN","oi":33245,"mp":0.0,"cp":0.3,"P":0,"F":0,"co":0.0,"L":50,"fl":"ENV|MM0"},{"n":"ALUMINUM MW US TR PLATTS SWAP - COMMODITY EXCHANGE INC.","c":"191693","oi":32341,"mp":0.0,"cp":-0.58,"P":0,"F":0,"co":0.0,"L":50,"fl":""},{"n":"NYISO ZONE J DA OFF-PK - ICE FUTURES ENERGY DIV","c":"0643BX","oi":32284,"mp":-1.3,"cp":-0.93,"P":0,"F":0,"co":0.0,"L":50,"fl":""},{"n":"PJM.AEP-DAYTON HUB_month_on_rtp - NODAL EXCHANGE","c":"064FKA","oi":32260,"mp":9.8,"cp":0.0,"P":0,"F":0,"co":0.0,"L":50,"fl":""},{"n":"PJM PSEG DAY-AHEAD PEAK - ICE FUTURES ENERGY DIV","c":"0643DL","oi":31587,"mp":3.7,"cp":1.25,"P":0,"F":0,"co":0.0,"L":50,"fl":""},{"n":"RGGI VINTAGE 2017 - ICE FUTURES ENERGY DIV","c":"0063AR","oi":31360,"mp":0.0,"cp":0.16,"P":0,"F":0,"co":0.0,"L":50,"fl":"ENV|MM0"},{"n":"PJM PSEG ZONE DAY-AHEAD OFF-PEAK - ICE FUTURES ENERGY DIV","c":"0643DM","oi":30427,"mp":-2.7,"cp":0.9,"P":0,"F":0,"co":0.0,"L":50,"fl":""},{"n":"PJM TRI-RECs CLASS 1 Vin 2021 - ICE FUTURES ENERGY DIV","c":"0063B1","oi":29888,"mp":0.0,"cp":0.0,"P":0,"F":0,"co":0.0,"L":50,"fl":"ENV|MM0"},{"n":"PJM TRI-RECs CLASS 1 Vin 2019 - ICE FUTURES ENERGY DIV","c":"0063AD","oi":29597,"mp":0.0,"cp":0.17,"P":0,"F":0,"co":0.0,"L":50,"fl":"ENV|MM0"},{"n":"NJ SRECS VINTAGE 2021 - ICE FUTURES ENERGY DIV","c":"0063BD","oi":29370,"mp":0.0,"cp":0.0,"P":0,"F":0,"co":0.0,"L":50,"fl":"ENV|MM0"},{"n":"USGC HSFO (PLATTS) - ICE FUTURES ENERGY DIV","c":"02141B","oi":28946,"mp":1.2,"cp":-0.73,"P":0,"F":0,"co":0.0,"L":50,"fl":""},{"n":"CAISO SP15 FIN DA OFF-PEAK - ICE FUTURES ENERGY DIV","c":"064396","oi":27500,"mp":0.5,"cp":0.0,"P":0,"F":0,"co":0.0,"L":50,"fl":""},{"n":"GULF JET NY HEAT OIL SPR SWAP - NEW YORK MERCANTILE EXCHANGE","c":"86465A","oi":27111,"mp":0.0,"cp":-1.79,"P":0,"F":0,"co":0.0,"L":50,"fl":"MM0"},{"n":"MISO IN. REAL-TIME OFF-PEAK - ICE FUTURES ENERGY DIV","c":"06439L","oi":26379,"mp":0.0,"cp":0.28,"P":0,"F":0,"co":0.0,"L":50,"fl":"MM0"},{"n":"PJM PECO ZONE DA PEAK - ICE FUTURES ENERGY DIV","c":"0643CZ","oi":26244,"mp":-0.2,"cp":1.22,"P":0,"F":0,"co":0.0,"L":50,"fl":""},{"n":"MICHCON FINANCIAL INDEX - ICE FUTURES ENERGY DIV","c":"0233AN","oi":25449,"mp":0.0,"cp":-0.24,"P":0,"F":0,"co":0.0,"L":50,"fl":"MM0"},{"n":"CHEESE (CASH-SETTLED) - CHICAGO MERCANTILE EXCHANGE","c":"063642","oi":25089,"mp":-1.8,"cp":0.54,"P":0,"F":0,"co":0.0,"L":50,"fl":""},{"n":"PJM.AEP-DAYTON HUB_month_off_rtp - NODAL EXCHANGE","c":"064FKB","oi":24930,"mp":6.1,"cp":0.0,"P":0,"F":0,"co":0.0,"L":50,"fl":""},{"n":"NYISO ZONE A DA OFF-PK - ICE FUTURES ENERGY DIV","c":"0643BZ","oi":23786,"mp":0.1,"cp":0.04,"P":0,"F":0,"co":0.0,"L":50,"fl":""},{"n":"NFX CS5TC CAPESIZE 5T/C AVG - NASDAQ FUTURES","c":"261P05","oi":23640,"mp":27.5,"cp":3.81,"P":-20,"F":20,"co":0.0,"L":50,"fl":""},{"n":"PJM PECO ZONE OFF-PEAK MONTHLY - ICE FUTURES ENERGY DIV","c":"0643D1","oi":23624,"mp":-0.4,"cp":1.35,"P":0,"F":0,"co":0.0,"L":50,"fl":""},{"n":"MID-C DAY-AHEAD OFF-PEAK - ICE FUTURES ENERGY DIV","c":"064392","oi":23460,"mp":0.5,"cp":-1.92,"P":0,"F":0,"co":0.0,"L":50,"fl":""},{"n":"CONWAY PROPANE (OPIS) - NEW YORK MERCANTILE EXCHANGE","c":"06665T","oi":22219,"mp":0.0,"cp":2.13,"P":0,"F":0,"co":0.0,"L":50,"fl":"MM0"},{"n":"PJM COMED ZONE DAY AHEAD LMP PEAK MONTHLY - ICE FUTURES ENERGY DIV","c":"0643CN","oi":20330,"mp":0.0,"cp":0.0,"P":0,"F":0,"co":0.0,"L":50,"fl":"MM0"},{"n":"PJM BGE ZONE DAY AHEAD, PEAK MONTHLY - ICE FUTURES ENERGY DIV","c":"0643CK","oi":20015,"mp":-6.4,"cp":-0.35,"P":0,"F":0,"co":0.0,"L":50,"fl":""},{"n":"MT BELV NAT GASOLINE OPIS SWAP - NEW YORK MERCANTILE EXCHANGE","c":"06665R","oi":19837,"mp":0.0,"cp":-0.98,"P":0,"F":0,"co":0.0,"L":50,"fl":"MM0"},{"n":"PJM BGE ZONE DAY AHEAD OFF PEAK MONTHLY - ICE FUTURES ENERGY DIV","c":"0643CJ","oi":19655,"mp":-2.5,"cp":-0.36,"P":0,"F":0,"co":0.0,"L":50,"fl":""},{"n":"GULF NO6 FO 3% v EUR 3.5% RDAM - NEW YORK MERCANTILE EXCHANGE","c":"021A28","oi":19394,"mp":0.9,"cp":0.03,"P":0,"F":0,"co":0.0,"L":50,"fl":""},{"n":"PROPANE OPIS MT BELV NONTET FP - ICE FUTURES ENERGY DIV","c":"06641F","oi":19290,"mp":0.0,"cp":-1.62,"P":0,"F":0,"co":0.0,"L":50,"fl":"MM0"},{"n":"GULF COAST UNL 87 GAS M2 PL RB - NEW YORK MERCANTILE EXCHANGE","c":"111A31","oi":18499,"mp":0.0,"cp":0.0,"P":0,"F":0,"co":0.0,"L":50,"fl":"MM0|FLOW-NA"},{"n":"NAPHTHA CRACK SPR SWAP - NEW YORK MERCANTILE EXCHANGE","c":"86665A","oi":17913,"mp":-1.3,"cp":1.1,"P":0,"F":0,"co":0.0,"L":50,"fl":""},{"n":"GASOLINE CRK-RBOB/BRENT 1st - ICE FUTURES ENERGY DIV","c":"111415","oi":17574,"mp":0.0,"cp":-2.56,"P":0,"F":0,"co":0.0,"L":50,"fl":"MM0"},{"n":"PJM COMED ZONE DAY AHEAD LMP OFF-PEAK MONTHLY - ICE FUTURES ENERGY DIV","c":"0643CM","oi":15880,"mp":0.0,"cp":0.0,"P":0,"F":0,"co":0.0,"L":50,"fl":"MM0"},{"n":"RBOB CALENDAR SWAP - NEW YORK MERCANTILE EXCHANGE","c":"11165K","oi":15872,"mp":0.0,"cp":0.0,"P":0,"F":0,"co":0.0,"L":50,"fl":"MM0"},{"n":"NFX SM6TC SUPRAMAX 6T/C AVG - NASDAQ FUTURES","c":"261P09","oi":15666,"mp":-3.7,"cp":0.0,"P":0,"F":0,"co":0.0,"L":50,"fl":""},{"n":"NAT GASLNE OPIS MT B NONTET FP - ICE FUTURES ENERGY DIV","c":"06641A","oi":15485,"mp":0.0,"cp":-1.19,"P":0,"F":0,"co":0.0,"L":50,"fl":"MM0"},{"n":"WCS OIL NET ENERGY MONTHLY IND - NEW YORK MERCANTILE EXCHANGE","c":"067A75","oi":11276,"mp":-5.6,"cp":-0.27,"P":0,"F":0,"co":0.0,"L":50,"fl":""},{"n":"ERCOT - NORTH MONTHLY OFF-PEAK - ICE FUTURES ENERGY DIV","c":"0643A8","oi":10664,"mp":0.9,"cp":2.1,"P":0,"F":0,"co":0.0,"L":50,"fl":""},{"n":"BUTANE OPIS MT BELV NONTET FP  - ICE FUTURES ENERGY DIV","c":"06641D","oi":10305,"mp":0.0,"cp":-0.78,"P":0,"F":0,"co":0.0,"L":50,"fl":"MM0"},{"n":"3.5% FUEL OIL RDAM CRACK SPR  - NEW YORK MERCANTILE EXCHANGE","c":"86565C","oi":9394,"mp":-3.8,"cp":0.83,"P":0,"F":0,"co":0.0,"L":50,"fl":""},{"n":"EUR 3.5% FUEL OIL RTD CAL - NEW YORK MERCANTILE EXCHANGE","c":"02165E","oi":9019,"mp":0.3,"cp":1.57,"P":0,"F":0,"co":0.0,"L":50,"fl":""},{"n":"SING JET KERO GASOIL SPR SWAP - NEW YORK MERCANTILE EXCHANGE","c":"86465C","oi":8900,"mp":0.3,"cp":0.0,"P":0,"F":0,"co":0.0,"L":50,"fl":""},{"n":"SING 380 FUEL OIL SWAP - NEW YORK MERCANTILE EXCHANGE","c":"02165K","oi":8638,"mp":0.0,"cp":2.1,"P":0,"F":0,"co":0.0,"L":50,"fl":"MM0"},{"n":"MINI SING 380 FUEL OIL SWAP - NEW YORK MERCANTILE EXCHANGE","c":"021A35","oi":6902,"mp":0.0,"cp":6.22,"P":0,"F":0,"co":0.0,"L":50,"fl":"MM0"},{"n":"BUTTER (CASH SETTLED) - CHICAGO MERCANTILE EXCHANGE","c":"050642","oi":6623,"mp":-1.3,"cp":6.48,"P":0,"F":0,"co":0.0,"L":50,"fl":""},{"n":"NON FAT DRY MILK - CHICAGO MERCANTILE EXCHANGE","c":"052642","oi":6252,"mp":-5.5,"cp":-1.41,"P":0,"F":0,"co":0.0,"L":50,"fl":""},{"n":"NFX SM10TC SUPRAMAX 10T/C AVG - NASDAQ FUTURES","c":"261P08","oi":5820,"mp":-4.1,"cp":0.0,"P":0,"F":0,"co":0.0,"L":50,"fl":"FLOW-NA"},{"n":"Mini Eur Naphtha CIF NWE Swap - NEW YORK MERCANTILE EXCHANGE","c":"03265J","oi":5674,"mp":0.0,"cp":-6.82,"P":0,"F":0,"co":0.0,"L":50,"fl":"MM0"},{"n":"ETHANOL T2 FOB INCL DUTY SWAP - NEW YORK MERCANTILE EXCHANGE","c":"025608","oi":5209,"mp":0.0,"cp":-0.58,"P":0,"F":0,"co":0.0,"L":50,"fl":"MM0"},{"n":"ARGUS PROPANE FAR EAST INDEX - NEW YORK MERCANTILE EXCHANGE","c":"06665B","oi":4923,"mp":0.0,"cp":-2.05,"P":0,"F":0,"co":0.0,"L":50,"fl":"MM0"},{"n":"FUEL OIL-380cst SING/3.5% RDAM - NEW YORK MERCANTILE EXCHANGE","c":"021A56","oi":4277,"mp":0.0,"cp":-0.35,"P":0,"F":0,"co":0.0,"L":50,"fl":"MM0"},{"n":"DRY WHEY - CHICAGO MERCANTILE EXCHANGE","c":"052645","oi":4224,"mp":0.0,"cp":0.31,"P":0,"F":0,"co":0.0,"L":50,"fl":"MM0"},{"n":"EUROPEAN NAPHTHA CAL - NEW YORK MERCANTILE EXCHANGE","c":"03265A","oi":3621,"mp":0.0,"cp":0.83,"P":0,"F":0,"co":0.0,"L":50,"fl":"MM0"},{"n":"ARGUS FAR EAST SWAP PROPANE - ICE FUTURES ENERGY DIV","c":"066413","oi":3452,"mp":0.0,"cp":0.93,"P":0,"F":0,"co":0.0,"L":50,"fl":"MM0"},{"n":"MINI JAPAN C&F NAPHTHA - NEW YORK MERCANTILE EXCHANGE","c":"86665E","oi":1778,"mp":0.0,"cp":5.62,"P":0,"F":0,"co":0.0,"L":50,"fl":"MM0"},{"n":"CRUDE OIL, LIGHT SWEET - NEW YORK MERCANTILE EXCHANGE","c":"067651","oi":2110793,"mp":6.4,"cp":1.28,"P":0,"F":10,"co":2.5,"L":51,"fl":""},{"n":"CORN - CHICAGO BOARD OF TRADE","c":"002602","oi":1760527,"mp":0.9,"cp":0.85,"P":0,"F":10,"co":2.5,"L":51,"fl":""},{"n":"SOYBEANS - CHICAGO BOARD OF TRADE","c":"005602","oi":747077,"mp":-6.6,"cp":1.18,"P":0,"F":10,"co":2.5,"L":51,"fl":""},{"n":"CRUDE OIL, LIGHT SWEET-WTI - ICE FUTURES EUROPE","c":"067411","oi":616654,"mp":2.1,"cp":0.45,"P":0,"F":10,"co":2.5,"L":51,"fl":""},{"n":"HSC FIN BASIS - ICE FUTURES ENERGY DIV","c":"023398","oi":539435,"mp":0.3,"cp":0.43,"P":0,"F":10,"co":2.5,"L":51,"fl":""},{"n":"NWP ROCKIES FIN BASIS - ICE FUTURES ENERGY DIV","c":"023395","oi":306713,"mp":0.6,"cp":0.38,"P":0,"F":10,"co":2.5,"L":51,"fl":""},{"n":"COTTON NO. 2 - ICE FUTURES U.S.","c":"033661","oi":253234,"mp":15.8,"cp":3.68,"P":-10,"F":20,"co":2.5,"L":51,"fl":""},{"n":"COPPER-GRADE #1 - COMMODITY EXCHANGE INC.","c":"085692","oi":241052,"mp":-3.3,"cp":1.25,"P":0,"F":10,"co":2.5,"L":51,"fl":""},{"n":"HOUSTON SHIP CHANNEL (INDEX) - ICE FUTURES ENERGY DIV","c":"0233AM","oi":201520,"mp":0.0,"cp":0.42,"P":0,"F":10,"co":2.5,"L":51,"fl":"MM0"},{"n":"HENRY HUB PENULTIMATE FIN - NEW YORK MERCANTILE EXCHANGE","c":"023A56","oi":91415,"mp":5.0,"cp":0.82,"P":0,"F":10,"co":2.5,"L":51,"fl":""},{"n":"ISO NE MASS HUB DA OFF-PK - ICE FUTURES ENERGY DIV","c":"0643BF","oi":90541,"mp":0.0,"cp":0.82,"P":0,"F":10,"co":2.5,"L":51,"fl":"MM0"},{"n":"PJM.WESTERN HUB_month_on_rtp - NODAL EXCHANGE","c":"064FKE","oi":59695,"mp":-13.8,"cp":0.2,"P":10,"F":0,"co":2.5,"L":51,"fl":""},{"n":"FEEDER CATTLE - CHICAGO MERCANTILE EXCHANGE","c":"061641","oi":49128,"mp":-10.0,"cp":0.68,"P":10,"F":0,"co":2.5,"L":51,"fl":""},{"n":"SP15 FIN DA PEAK FIXED - ICE FUTURES ENERGY DIV","c":"064395","oi":41017,"mp":-11.9,"cp":-0.07,"P":10,"F":0,"co":2.5,"L":51,"fl":""},{"n":"MILK, Class III - CHICAGO MERCANTILE EXCHANGE","c":"052641","oi":29876,"mp":-12.1,"cp":1.62,"P":10,"F":0,"co":2.5,"L":51,"fl":""},{"n":"3% FUEL OIL USGC VS. 3.5%FUEL OIL FOB ROTTERDAM BARGES - ICE FUTURES ENERGY DIV","c":"02141C","oi":23945,"mp":0.4,"cp":2.19,"P":0,"F":10,"co":2.5,"L":51,"fl":""},{"n":"MISO.INDIANA.HUB_month_on_dap - NODAL EXCHANGE","c":"064BFI","oi":17157,"mp":-12.8,"cp":-2.33,"P":10,"F":0,"co":2.5,"L":51,"fl":""},{"n":"MISO.INDIANA.HUB_month_off_dap - NODAL EXCHANGE","c":"064BFJ","oi":11225,"mp":-11.3,"cp":0.0,"P":10,"F":0,"co":2.5,"L":51,"fl":""},{"n":"PJM.PEPCO_month_off_dap - NODAL EXCHANGE","c":"064EVH","oi":11145,"mp":-17.7,"cp":0.0,"P":10,"F":0,"co":2.5,"L":51,"fl":"FLOW-NA"},{"n":"ROUGH RICE - CHICAGO BOARD OF TRADE","c":"039601","oi":8515,"mp":-24.1,"cp":1.27,"P":10,"F":0,"co":2.5,"L":51,"fl":""},{"n":"RANDOM LENGTH LUMBER - CHICAGO MERCANTILE EXCHANGE","c":"058643","oi":4203,"mp":-12.9,"cp":-5.73,"P":10,"F":0,"co":2.5,"L":51,"fl":""},{"n":"SOYBEAN OIL - CHICAGO BOARD OF TRADE","c":"007601","oi":570844,"mp":-12.3,"cp":1.95,"P":10,"F":10,"co":5.0,"L":53,"fl":""},{"n":"SOYBEAN MEAL - CHICAGO BOARD OF TRADE","c":"026603","oi":508053,"mp":0.4,"cp":3.69,"P":0,"F":20,"co":5.0,"L":53,"fl":""},{"n":"#2 HEATING OIL- NY HARBOR-ULSD - NEW YORK MERCANTILE EXCHANGE","c":"022651","oi":373280,"mp":8.4,"cp":3.1,"P":0,"F":20,"co":5.0,"L":53,"fl":""},{"n":"WHEAT-HRW - CHICAGO BOARD OF TRADE","c":"001612","oi":329717,"mp":-1.3,"cp":2.62,"P":0,"F":20,"co":5.0,"L":53,"fl":""},{"n":"COFFEE C - ICE FUTURES U.S.","c":"083731","oi":248312,"mp":-11.0,"cp":1.62,"P":10,"F":10,"co":5.0,"L":53,"fl":""},{"n":"HENRY HUB PENULTIMATE GAS SWAP - NEW YORK MERCANTILE EXCHANGE","c":"03565C","oi":163965,"mp":5.2,"cp":2.82,"P":0,"F":20,"co":5.0,"L":53,"fl":""},{"n":"WTI  HOUSTON ARGUS/WTI TR MO - NEW YORK MERCANTILE EXCHANGE","c":"0676A5","oi":135542,"mp":0.0,"cp":1.79,"P":0,"F":20,"co":5.0,"L":53,"fl":"MM0"},{"n":"PG&E CITYGATE FIN BASIS - ICE FUTURES ENERGY DIV","c":"023394","oi":132141,"mp":0.3,"cp":0.4,"P":0,"F":20,"co":5.0,"L":53,"fl":""},{"n":"PLATINUM - NEW YORK MERCANTILE EXCHANGE","c":"076651","oi":70152,"mp":12.9,"cp":3.66,"P":-10,"F":30,"co":5.0,"L":53,"fl":""},{"n":"NFX PM4TC PANAMAX 4T/C AVG - NASDAQ FUTURES","c":"261P07","oi":39996,"mp":10.3,"cp":3.07,"P":-10,"F":30,"co":5.0,"L":53,"fl":""},{"n":"COAL (API 2) CIF ARA SWAP FUT - NEW YORK MERCANTILE EXCHANGE","c":"024656","oi":28318,"mp":-28.3,"cp":-1.0,"P":20,"F":0,"co":5.0,"L":53,"fl":""},{"n":"CBT ETHANOL - CHICAGO BOARD OF TRADE","c":"025601","oi":2598,"mp":-39.4,"cp":4.66,"P":20,"F":0,"co":5.0,"L":53,"fl":""},{"n":"SUGAR NO. 11 - ICE FUTURES U.S.","c":"080732","oi":789728,"mp":5.0,"cp":3.39,"P":0,"F":30,"co":7.5,"L":54,"fl":""},{"n":"CANOLA - ICE FUTURES U.S.","c":"135731","oi":166224,"mp":-16.0,"cp":3.24,"P":10,"F":20,"co":7.5,"L":54,"fl":""},{"n":"PJM.PECO_month_on_dap - NODAL EXCHANGE","c":"064EUY","oi":37325,"mp":7.8,"cp":4.25,"P":0,"F":30,"co":7.5,"L":54,"fl":""},{"n":"PJM.PECO_month_off_dap - NODAL EXCHANGE","c":"064EUZ","oi":35010,"mp":6.8,"cp":4.81,"P":0,"F":30,"co":7.5,"L":54,"fl":""},{"n":"SILVER - COMMODITY EXCHANGE INC.","c":"084691","oi":224346,"mp":-18.2,"cp":6.39,"P":10,"F":30,"co":10.0,"L":55,"fl":""},{"n":"FRZN CONCENTRATED ORANGE JUICE - ICE FUTURES U.S.","c":"040701","oi":18699,"mp":-39.3,"cp":2.7,"P":20,"F":20,"co":10.0,"L":55,"fl":""},{"n":"GOLD - COMMODITY EXCHANGE INC.","c":"088691","oi":539520,"mp":-14.7,"cp":6.73,"P":10,"F":40,"co":12.5,"L":56,"fl":""},{"n":"PJM.BGE_month_off_dap - NODAL EXCHANGE","c":"064DPR","oi":24670,"mp":-46.6,"cp":9.77,"P":30,"F":30,"co":15.0,"L":58,"fl":""},{"n":"PJM.BGE_month_on_dap - NODAL EXCHANGE","c":"064DPQ","oi":24570,"mp":-47.3,"cp":9.81,"P":30,"F":30,"co":15.0,"L":58,"fl":""}]}