{"date":"2020-04-07","rows":[{"n":"PJM.PECO_month_on_dap - NODAL EXCHANGE","c":"064EUY","oi":56945,"mp":10.3,"cp":-6.57,"P":-10,"F":-30,"co":-10.0,"L":45,"fl":""},{"n":"MICHCON FINANCIAL INDEX - ICE FUTURES ENERGY DIV","c":"0233AN","oi":37016,"mp":0.0,"cp":-4.03,"P":0,"F":-40,"co":-10.0,"L":45,"fl":"MM0"},{"n":"CHICAGO CITYGATE (INDEX) - ICE FUTURES ENERGY DIV","c":"02339Q","oi":28414,"mp":0.0,"cp":-5.18,"P":0,"F":-40,"co":-10.0,"L":45,"fl":"MM0"},{"n":"NON FAT DRY MILK - CHICAGO MERCANTILE EXCHANGE","c":"052642","oi":9655,"mp":0.7,"cp":-6.08,"P":0,"F":-40,"co":-10.0,"L":45,"fl":""},{"n":"COLUMBIA GAS CO. - TCO POOL (APPALACHIA) (BASIS) - ICE FUTURES ENERGY DIV","c":"02339W","oi":195376,"mp":0.0,"cp":-2.85,"P":0,"F":-30,"co":-7.5,"L":46,"fl":"MM0"},{"n":"SILVER - COMMODITY EXCHANGE INC.","c":"084691","oi":138974,"mp":12.0,"cp":-1.21,"P":-10,"F":-20,"co":-7.5,"L":46,"fl":""},{"n":"WTI-BRENT CALENDAR - NEW YORK MERCANTILE EXCHANGE","c":"06765L","oi":124220,"mp":-3.1,"cp":-11.53,"P":0,"F":-30,"co":-7.5,"L":46,"fl":""},{"n":"HENRY HUB PENULTIMATE FIN - NEW YORK MERCANTILE EXCHANGE","c":"023A56","oi":111753,"mp":-16.0,"cp":-4.57,"P":10,"F":-40,"co":-7.5,"L":46,"fl":""},{"n":"CALIF CARBON VINTAGE 2020 - ICE FUTURES ENERGY DIV","c":"0063CA","oi":102930,"mp":22.6,"cp":-2.55,"P":-10,"F":-20,"co":-7.5,"L":46,"fl":"ENV"},{"n":"ISONE..H.INTERNAL_HUB_month_off_dap - NODAL EXCHANGE","c":"064AAB","oi":66493,"mp":-6.4,"cp":-3.12,"P":0,"F":-30,"co":-7.5,"L":46,"fl":""},{"n":"PJM.PSEG_month_on_dap - NODAL EXCHANGE","c":"064EXE","oi":60345,"mp":24.7,"cp":-1.59,"P":-10,"F":-20,"co":-7.5,"L":46,"fl":""},{"n":"PJM.N ILLINOIS HUB_month_off_rtp - NODAL EXCHANGE","c":"064FKD","oi":52270,"mp":69.0,"cp":0.17,"P":-30,"F":0,"co":-7.5,"L":46,"fl":""},{"n":"PJM.N ILLINOIS HUB_month_on_rtp - NODAL EXCHANGE","c":"064FKC","oi":42520,"mp":45.5,"cp":0.38,"P":-30,"F":0,"co":-7.5,"L":46,"fl":""},{"n":"MARYLAND SOLAR REC - ICE FUTURES ENERGY DIV","c":"0063DN","oi":34062,"mp":-3.9,"cp":-5.87,"P":0,"F":-30,"co":-7.5,"L":46,"fl":"ENV"},{"n":"BLACK SEA WHEAT FINANCIAL - CHICAGO BOARD OF TRADE","c":"00160F","oi":22787,"mp":44.8,"cp":-2.02,"P":-30,"F":0,"co":-7.5,"L":46,"fl":""},{"n":"BUTTER (CASH SETTLED) - CHICAGO MERCANTILE EXCHANGE","c":"050642","oi":10773,"mp":-1.2,"cp":-6.13,"P":0,"F":-30,"co":-7.5,"L":46,"fl":""},{"n":"WAHA FIN BASIS - ICE FUTURES ENERGY DIV","c":"023399","oi":436197,"mp":-0.1,"cp":-1.48,"P":0,"F":-20,"co":-5.0,"L":48,"fl":""},{"n":"MICHIGAN CONSOLIDATED CITYGATE (GENERIC) (BASIS) - ICE FUTURES ENERGY DIV","c":"0233AQ","oi":281178,"mp":-0.6,"cp":-1.04,"P":0,"F":-20,"co":-5.0,"L":48,"fl":""},{"n":"BRENT CRUDE OIL LAST DAY - NEW YORK MERCANTILE EXCHANGE","c":"06765T","oi":257470,"mp":-2.4,"cp":-2.92,"P":0,"F":-20,"co":-5.0,"L":48,"fl":""},{"n":"LEAN HOGS - CHICAGO MERCANTILE EXCHANGE","c":"054642","oi":227151,"mp":7.9,"cp":-2.58,"P":0,"F":-20,"co":-5.0,"L":48,"fl":""},{"n":"NATURAL GAS PENULTIMATE ICE - ICE FUTURES ENERGY DIV","c":"023392","oi":214720,"mp":-4.9,"cp":-3.46,"P":0,"F":-20,"co":-5.0,"L":48,"fl":""},{"n":"PANHANDLE EASTERN- POOL GAS (BASIS) - ICE FUTURES ENERGY DIV","c":"0233BL","oi":201639,"mp":0.0,"cp":-1.67,"P":0,"F":-20,"co":-5.0,"L":48,"fl":"MM0"},{"n":"NJ SRECS - ICE FUTURES ENERGY DIV","c":"0063CC","oi":178037,"mp":8.2,"cp":-3.62,"P":0,"F":-20,"co":-5.0,"L":48,"fl":"ENV"},{"n":"PG&E CITYGATE FIN BASIS - ICE FUTURES ENERGY DIV","c":"023394","oi":149426,"mp":0.0,"cp":-2.27,"P":0,"F":-20,"co":-5.0,"L":48,"fl":"MM0"},{"n":"ERCOT NORTH 345KV RT PK FIX - ICE FUTURES ENERGY DIV","c":"06439R","oi":90068,"mp":8.7,"cp":-1.79,"P":0,"F":-20,"co":-5.0,"L":48,"fl":""},{"n":"ISONE..H.INTERNAL_HUB_month_on_dap - NODAL EXCHANGE","c":"064AAA","oi":79683,"mp":-4.7,"cp":-1.77,"P":0,"F":-20,"co":-5.0,"L":48,"fl":""},{"n":"PJM AEP DAYTON RT PEAK FIXED - ICE FUTURES ENERGY DIV","c":"06439B","oi":77128,"mp":29.2,"cp":-0.3,"P":-20,"F":0,"co":-5.0,"L":48,"fl":""},{"n":"PJM AEP DAYTON RT OFF-PK - ICE FUTURES ENERGY DIV","c":"06439A","oi":58768,"mp":26.5,"cp":-0.03,"P":-20,"F":0,"co":-5.0,"L":48,"fl":""},{"n":"CALIF CARBON ALL VINTAGE 2019 - ICE FUTURES ENERGY DIV","c":"0063AS","oi":43279,"mp":39.5,"cp":0.35,"P":-20,"F":0,"co":-5.0,"L":48,"fl":"ENV"},{"n":"MID-C DAY-AHEAD PEAK - ICE FUTURES ENERGY DIV","c":"064391","oi":39980,"mp":0.9,"cp":-2.89,"P":0,"F":-20,"co":-5.0,"L":48,"fl":""},{"n":"PJM.JCPL_month_on_dap - NODAL EXCHANGE","c":"064EJI","oi":32329,"mp":39.7,"cp":0.12,"P":-20,"F":0,"co":-5.0,"L":48,"fl":""},{"n":"PJM.BGE_month_on_dap - NODAL EXCHANGE","c":"064DPQ","oi":22591,"mp":-17.5,"cp":-5.25,"P":10,"F":-30,"co":-5.0,"L":48,"fl":""},{"n":"PJM.BGE_month_off_dap - NODAL EXCHANGE","c":"064DPR","oi":22361,"mp":-22.6,"cp":-5.43,"P":10,"F":-30,"co":-5.0,"L":48,"fl":""},{"n":"NATURAL GAS HENRY LD1 FIXED - ICE FUTURES ENERGY DIV","c":"023391","oi":5664523,"mp":5.8,"cp":-1.8,"P":0,"F":-10,"co":-2.5,"L":49,"fl":""},{"n":"CRUDE OIL, LIGHT SWEET - NEW YORK MERCANTILE EXCHANGE","c":"067651","oi":2342227,"mp":7.7,"cp":-1.95,"P":0,"F":-10,"co":-2.5,"L":49,"fl":""},{"n":"SOYBEANS - CHICAGO BOARD OF TRADE","c":"005602","oi":821968,"mp":2.1,"cp":-0.75,"P":0,"F":-10,"co":-2.5,"L":49,"fl":""},{"n":"HSC FIN BASIS - ICE FUTURES ENERGY DIV","c":"023398","oi":567042,"mp":0.0,"cp":-0.58,"P":0,"F":-10,"co":-2.5,"L":49,"fl":"MM0"},{"n":"GOLD - COMMODITY EXCHANGE INC.","c":"088691","oi":480050,"mp":31.8,"cp":1.74,"P":-20,"F":10,"co":-2.5,"L":49,"fl":""},{"n":"SOYBEAN OIL - CHICAGO BOARD OF TRADE","c":"007601","oi":456623,"mp":0.7,"cp":-2.05,"P":0,"F":-10,"co":-2.5,"L":49,"fl":""},{"n":"GASOLINE BLENDSTOCK (RBOB)  - NEW YORK MERCANTILE EXCHANGE","c":"111659","oi":367672,"mp":9.5,"cp":-0.37,"P":0,"F":-10,"co":-2.5,"L":49,"fl":""},{"n":"#2 HEATING OIL- NY HARBOR-ULSD - NEW YORK MERCANTILE EXCHANGE","c":"022651","oi":357444,"mp":-0.4,"cp":-0.62,"P":0,"F":-10,"co":-2.5,"L":49,"fl":""},{"n":"COLORADO INTERSTATE - MAINLINE (BASIS) - ICE FUTURES ENERGY DIV","c":"02339U","oi":308426,"mp":-1.1,"cp":-1.04,"P":0,"F":-10,"co":-2.5,"L":49,"fl":""},{"n":"HENRY HUB LAST DAY FIN - NEW YORK MERCANTILE EXCHANGE","c":"023A55","oi":274693,"mp":2.1,"cp":-0.72,"P":0,"F":-10,"co":-2.5,"L":49,"fl":""},{"n":"PJM WESTERN HUB RT PEAK MINI - ICE FUTURES ENERGY DIV","c":"0643DF","oi":270652,"mp":3.5,"cp":-1.66,"P":0,"F":-10,"co":-2.5,"L":49,"fl":""},{"n":"TEXAS EASTERN- M3 ZONE (DELIVERED) (BASIS) - ICE FUTURES ENERGY DIV","c":"0233CH","oi":246891,"mp":0.5,"cp":-0.31,"P":0,"F":-10,"co":-2.5,"L":49,"fl":""},{"n":"WHEAT-HRW - CHICAGO BOARD OF TRADE","c":"001612","oi":226234,"mp":0.9,"cp":-0.46,"P":0,"F":-10,"co":-2.5,"L":49,"fl":""},{"n":"REX ZONE 3 BASIS - ICE FUTURES ENERGY DIV","c":"0233EB","oi":209705,"mp":0.0,"cp":-0.66,"P":0,"F":-10,"co":-2.5,"L":49,"fl":"MM0"},{"n":"EL PASO - PERMIAN BASIN (BASIS) - ICE FUTURES ENERGY DIV","c":"0233A5","oi":205891,"mp":-0.0,"cp":-0.39,"P":0,"F":-10,"co":-2.5,"L":49,"fl":""},{"n":"WTI  HOUSTON ARGUS/WTI TR MO - NEW YORK MERCANTILE EXCHANGE","c":"0676A5","oi":202972,"mp":8.0,"cp":-0.39,"P":0,"F":-10,"co":-2.5,"L":49,"fl":""},{"n":"COPPER-GRADE #1 - COMMODITY EXCHANGE INC.","c":"085692","oi":185408,"mp":-14.2,"cp":-0.59,"P":10,"F":-20,"co":-2.5,"L":49,"fl":""},{"n":"CANOLA - ICE FUTURES U.S.","c":"135731","oi":169854,"mp":-22.1,"cp":-2.9,"P":10,"F":-20,"co":-2.5,"L":49,"fl":""},{"n":"HENRY HUB PENULTIMATE NAT GAS - NEW YORK MERCANTILE EXCHANGE","c":"03565C","oi":148243,"mp":-4.5,"cp":-0.7,"P":0,"F":-10,"co":-2.5,"L":49,"fl":""},{"n":"PJM WESTERN HUB RT OFF - ICE FUTURES ENERGY DIV","c":"064394","oi":138413,"mp":-0.5,"cp":-1.18,"P":0,"F":-10,"co":-2.5,"L":49,"fl":""},{"n":"PJM.WESTERN HUB_month_off_dap - NODAL EXCHANGE","c":"064FHL","oi":135065,"mp":-1.9,"cp":-0.43,"P":0,"F":-10,"co":-2.5,"L":49,"fl":""},{"n":"HOUSTON SHIP CHANNEL (INDEX) - ICE FUTURES ENERGY DIV","c":"0233AM","oi":119165,"mp":0.0,"cp":-0.68,"P":0,"F":-10,"co":-2.5,"L":49,"fl":"MM0"},{"n":"PJM WESTERN HUB DA PEAK - ICE FUTURES ENERGY DIV","c":"0643DC","oi":116165,"mp":1.0,"cp":-0.66,"P":0,"F":-10,"co":-2.5,"L":49,"fl":""},{"n":"ALGONQUIN CITY-GATES FINANCIAL BASIS - ICE FUTURES ENERGY DIV","c":"02339E","oi":100457,"mp":0.0,"cp":-1.21,"P":0,"F":-10,"co":-2.5,"L":49,"fl":"MM0"},{"n":"ISO NE MASS HUB DA PEAK - ICE FUTURES ENERGY DIV","c":"0643BG","oi":88846,"mp":-1.2,"cp":-0.6,"P":0,"F":-10,"co":-2.5,"L":49,"fl":""},{"n":"PJM.PECO_month_off_dap - NODAL EXCHANGE","c":"064EUZ","oi":49345,"mp":11.7,"cp":-0.18,"P":-10,"F":0,"co":-2.5,"L":49,"fl":""},{"n":"PJM.PSEG_month_off_dap - NODAL EXCHANGE","c":"064EXF","oi":48764,"mp":13.2,"cp":-0.22,"P":-10,"F":0,"co":-2.5,"L":49,"fl":""},{"n":"CALIF CARBON ALLOWANCE V2022 - ICE FUTURES ENERGY DIV","c":"0063D9","oi":33254,"mp":10.3,"cp":-0.15,"P":-10,"F":0,"co":-2.5,"L":49,"fl":"ENV"},{"n":"PJM.ATSI_month_on_dap - NODAL EXCHANGE","c":"064FZA","oi":28135,"mp":14.1,"cp":0.48,"P":-10,"F":0,"co":-2.5,"L":49,"fl":""},{"n":"PJM.ATSI_month_off_dap - NODAL EXCHANGE","c":"064FZB","oi":27525,"mp":12.9,"cp":0.29,"P":-10,"F":0,"co":-2.5,"L":49,"fl":""},{"n":"PJM.PEPCO_month_on_dap - NODAL EXCHANGE","c":"064EVG","oi":20735,"mp":-22.6,"cp":-2.8,"P":10,"F":-20,"co":-2.5,"L":49,"fl":""},{"n":"ROUGH RICE - CHICAGO BOARD OF TRADE","c":"039601","oi":12096,"mp":13.5,"cp":-3.65,"P":-10,"F":0,"co":-2.5,"L":49,"fl":""},{"n":"PALLADIUM - NEW YORK MERCANTILE EXCHANGE","c":"075651","oi":7769,"mp":13.4,"cp":0.72,"P":-10,"F":0,"co":-2.5,"L":49,"fl":""},{"n":"AECO FIN BASIS - ICE FUTURES ENERGY DIV","c":"023396","oi":907870,"mp":-0.2,"cp":0.23,"P":0,"F":0,"co":0.0,"L":50,"fl":""},{"n":"DOMINION - SOUTH POINT (BASIS) - ICE FUTURES ENERGY DIV","c":"0233A3","oi":596427,"mp":-0.2,"cp":-0.04,"P":0,"F":0,"co":0.0,"L":50,"fl":""},{"n":"NWP ROCKIES FIN BASIS - ICE FUTURES ENERGY DIV","c":"023395","oi":349051,"mp":1.0,"cp":-0.2,"P":0,"F":0,"co":0.0,"L":50,"fl":""},{"n":"COLUMBIA GULF TRANSMISSION CO. -  MAINLINE POOL - ICE FUTURES ENERGY DIV","c":"02339Y","oi":305603,"mp":-0.9,"cp":0.1,"P":0,"F":0,"co":0.0,"L":50,"fl":""},{"n":"SOCAL BORDER FIN BASIS - ICE FUTURES ENERGY DIV","c":"023393","oi":277721,"mp":-1.1,"cp":0.29,"P":0,"F":0,"co":0.0,"L":50,"fl":""},{"n":"COFFEE C - ICE FUTURES U.S.","c":"083731","oi":240509,"mp":8.1,"cp":0.0,"P":0,"F":0,"co":0.0,"L":50,"fl":""},{"n":"NATURAL GAS PIPELINE-TEXOK (BASIS) - ICE FUTURES ENERGY DIV","c":"0233B1","oi":234752,"mp":0.0,"cp":-0.08,"P":0,"F":0,"co":0.0,"L":50,"fl":"MM0"},{"n":"PACIFIC GAS TRANSMISSION - MALIN (BASIS) - ICE FUTURES ENERGY DIV","c":"0233BH","oi":197391,"mp":0.0,"cp":0.2,"P":0,"F":0,"co":0.0,"L":50,"fl":"MM0"},{"n":"NORTHERN NATURAL GAS - VENTURA (BASIS) - ICE FUTURES ENERGY DIV","c":"0233BB","oi":197232,"mp":-0.2,"cp":-0.05,"P":0,"F":0,"co":0.0,"L":50,"fl":""},{"n":"COTTON NO. 2 - ICE FUTURES U.S.","c":"033661","oi":188501,"mp":-12.1,"cp":-1.67,"P":10,"F":-10,"co":0.0,"L":50,"fl":""},{"n":"PJM TRI-RECs CLASS 1  - ICE FUTURES ENERGY DIV","c":"0063CH","oi":153279,"mp":1.4,"cp":0.32,"P":0,"F":0,"co":0.0,"L":50,"fl":"ENV"},{"n":"WTI MIDLAND ARGUS VS WTI TRADE - NEW YORK MERCANTILE EXCHANGE","c":"067A71","oi":134152,"mp":1.8,"cp":0.18,"P":0,"F":0,"co":0.0,"L":50,"fl":""},{"n":"PJM.WESTERN HUB_month_on_rtp - NODAL EXCHANGE","c":"064FKE","oi":132972,"mp":1.8,"cp":0.29,"P":0,"F":0,"co":0.0,"L":50,"fl":""},{"n":"TRANSCO ZONE 6 BASIS - ICE FUTURES ENERGY DIV","c":"0233CU","oi":129826,"mp":-0.9,"cp":-0.14,"P":0,"F":0,"co":0.0,"L":50,"fl":""},{"n":"NAT GAS LD1 for GDD -TEXOK - ICE FUTURES ENERGY DIV","c":"0233AT","oi":121071,"mp":0.0,"cp":0.21,"P":0,"F":0,"co":0.0,"L":50,"fl":"MM0"},{"n":"PJM.WESTERN HUB_month_off_rtp - NODAL EXCHANGE","c":"064FKF","oi":111975,"mp":3.4,"cp":0.23,"P":0,"F":0,"co":0.0,"L":50,"fl":""},{"n":"NATURAL GAS PIPELINE-MID-CONTINENT POOL PIN (BASIS) - ICE FUTURES ENERGY DIV","c":"0233AY","oi":108644,"mp":0.0,"cp":0.33,"P":0,"F":0,"co":0.0,"L":50,"fl":"MM0"},{"n":"PJM WESTERN HUB DA OFF-PK - ICE FUTURES ENERGY DIV","c":"0643DB","oi":102017,"mp":1.2,"cp":-0.29,"P":0,"F":0,"co":0.0,"L":50,"fl":""},{"n":"PJM.AEP-DAYTON HUB_month_on_dap - NODAL EXCHANGE","c":"064DLW","oi":93466,"mp":13.0,"cp":0.92,"P":-10,"F":10,"co":0.0,"L":50,"fl":""},{"n":"PJM.AEP-DAYTON HUB_month_off_dap - NODAL EXCHANGE","c":"064DLX","oi":87686,"mp":14.0,"cp":0.86,"P":-10,"F":10,"co":0.0,"L":50,"fl":""},{"n":"NORTHWEST PIPELINE - CANADIAN BORDER (BASIS) - ICE FUTURES ENERGY DIV","c":"0233BC","oi":86313,"mp":0.0,"cp":-0.4,"P":0,"F":0,"co":0.0,"L":50,"fl":"MM0"},{"n":"PJM AEP DAYTON DA PEAK - ICE FUTURES ENERGY DIV","c":"06439F","oi":83668,"mp":0.4,"cp":0.43,"P":0,"F":0,"co":0.0,"L":50,"fl":""},{"n":"TEXAS EASTERN- M3 ZONE (DELIVERED) - ICE FUTURES ENERGY DIV","c":"0233CG","oi":70709,"mp":0.0,"cp":-0.59,"P":0,"F":0,"co":0.0,"L":50,"fl":"MM0"},{"n":"SP15 FIN DA PEAK FIXED - ICE FUTURES ENERGY DIV","c":"064395","oi":69396,"mp":-1.1,"cp":0.32,"P":0,"F":0,"co":0.0,"L":50,"fl":""},{"n":"PJM AEP DAYTON HUB DA OFF-PK  - ICE FUTURES ENERGY DIV","c":"06439C","oi":67830,"mp":0.4,"cp":0.2,"P":0,"F":0,"co":0.0,"L":50,"fl":""},{"n":"PJM N. IL HUB RT PEAK - ICE FUTURES ENERGY DIV","c":"0643BT","oi":66763,"mp":-3.4,"cp":-0.1,"P":0,"F":0,"co":0.0,"L":50,"fl":""},{"n":"PJM N. IL HUB DA PEAK - ICE FUTURES ENERGY DIV","c":"0643BE","oi":66052,"mp":-0.1,"cp":0.06,"P":0,"F":0,"co":0.0,"L":50,"fl":""},{"n":"PJM N. IL HUB DA OFF-PK  - ICE FUTURES ENERGY DIV","c":"0643BC","oi":62817,"mp":-0.1,"cp":-0.22,"P":0,"F":0,"co":0.0,"L":50,"fl":""},{"n":"CAISO NP-15 PEAK - ICE FUTURES ENERGY DIV","c":"0643BM","oi":60858,"mp":-5.8,"cp":-0.78,"P":0,"F":0,"co":0.0,"L":50,"fl":""},{"n":"PJM NI HUB RT OFF-PK - ICE FUTURES ENERGY DIV","c":"0643BS","oi":60372,"mp":1.0,"cp":0.31,"P":0,"F":0,"co":0.0,"L":50,"fl":""},{"n":"NYISO ZONE G DA PEAK - ICE FUTURES ENERGY DIV","c":"0643C3","oi":57862,"mp":-3.7,"cp":-0.27,"P":0,"F":0,"co":0.0,"L":50,"fl":""},{"n":"NYISO.HUD VL_month_on_dap - NODAL EXCHANGE","c":"064CXO","oi":57489,"mp":14.4,"cp":1.11,"P":-10,"F":10,"co":0.0,"L":50,"fl":""},{"n":"PLATINUM - NEW YORK MERCANTILE EXCHANGE","c":"076651","oi":54044,"mp":14.4,"cp":2.13,"P":-10,"F":10,"co":0.0,"L":50,"fl":""},{"n":"SOCAL CITYGATE FINANCIAL BASIS - ICE FUTURES ENERGY DIV","c":"0233BY","oi":51755,"mp":0.0,"cp":0.54,"P":0,"F":0,"co":0.0,"L":50,"fl":"MM0"},{"n":"CAISO NP-15 OFF-PEAK - ICE FUTURES ENERGY DIV","c":"0643BR","oi":51480,"mp":-0.4,"cp":-0.49,"P":0,"F":0,"co":0.0,"L":50,"fl":""},{"n":"MISO IN. DAY-AHEAD PEAK - ICE FUTURES ENERGY DIV","c":"0643AZ","oi":50148,"mp":0.0,"cp":-0.12,"P":0,"F":0,"co":0.0,"L":50,"fl":"MM0"},{"n":"PROPANE OPIS MT BELVIEU TET FP - ICE FUTURES ENERGY DIV","c":"06641G","oi":49406,"mp":-1.6,"cp":0.05,"P":0,"F":0,"co":0.0,"L":50,"fl":""},{"n":"ERCOT - NORTH MONTHLY OFF-PEAK - ICE FUTURES ENERGY DIV","c":"0643A8","oi":44983,"mp":-0.2,"cp":0.11,"P":0,"F":0,"co":0.0,"L":50,"fl":""},{"n":"MISO INDIANA  OFF-PEAK - ICE FUTURES ENERGY DIV","c":"06439K","oi":44366,"mp":0.0,"cp":-0.1,"P":0,"F":0,"co":0.0,"L":50,"fl":"MM0"},{"n":"MT BELV NAT GASOLINE OPIS - NEW YORK MERCANTILE EXCHANGE","c":"06665R","oi":40207,"mp":2.1,"cp":-0.44,"P":0,"F":0,"co":0.0,"L":50,"fl":""},{"n":"NYISO.HUD VL_month_off_dap - NODAL EXCHANGE","c":"064CXP","oi":39293,"mp":7.6,"cp":0.8,"P":0,"F":0,"co":0.0,"L":50,"fl":""},{"n":"MT BELVIEU ETHANE OPIS - NEW YORK MERCANTILE EXCHANGE","c":"06665P","oi":38123,"mp":1.8,"cp":0.84,"P":0,"F":0,"co":0.0,"L":50,"fl":""},{"n":"MISO INDIANA HUB RT PEAK - ICE FUTURES ENERGY DIV","c":"0643B3","oi":38006,"mp":-3.2,"cp":-0.02,"P":0,"F":0,"co":0.0,"L":50,"fl":""},{"n":"NYISO ZONE G DA OFF-PK - ICE FUTURES ENERGY DIV","c":"0643C4","oi":36517,"mp":0.6,"cp":0.36,"P":0,"F":0,"co":0.0,"L":50,"fl":""},{"n":"CAISO SP15 FIN DA OFF-PEAK - ICE FUTURES ENERGY DIV","c":"064396","oi":36445,"mp":-1.9,"cp":0.21,"P":0,"F":0,"co":0.0,"L":50,"fl":""},{"n":"PJM PPL ZONE DA PEAK - ICE FUTURES ENERGY DIV","c":"0643D8","oi":34977,"mp":0.4,"cp":0.94,"P":0,"F":0,"co":0.0,"L":50,"fl":""},{"n":"PJM PPL ZONE DAY AHEAD, OFF-PEAK MONTHLY - ICE FUTURES ENERGY DIV","c":"0643D7","oi":34802,"mp":0.4,"cp":0.66,"P":0,"F":0,"co":0.0,"L":50,"fl":""},{"n":"USGC HSFO (PLATTS) - ICE FUTURES ENERGY DIV","c":"02141B","oi":34537,"mp":0.0,"cp":-1.34,"P":0,"F":0,"co":0.0,"L":50,"fl":"MM0"},{"n":"RGGI VINTAGE 2019 - ICE FUTURES ENERGY DIV","c":"0063CL","oi":34469,"mp":7.5,"cp":0.0,"P":0,"F":0,"co":0.0,"L":50,"fl":"ENV"},{"n":"CALIF CARBON VINTAGE 2021 - ICE FUTURES ENERGY DIV","c":"0063CJ","oi":34287,"mp":7.8,"cp":1.43,"P":0,"F":0,"co":0.0,"L":50,"fl":"ENV"},{"n":"FEEDER CATTLE - CHICAGO MERCANTILE EXCHANGE","c":"061641","oi":34230,"mp":-0.9,"cp":-0.38,"P":0,"F":0,"co":0.0,"L":50,"fl":""},{"n":"ETHANE, MT. BELV-ENTERPRISE - ICE FUTURES ENERGY DIV","c":"066416","oi":32343,"mp":0.0,"cp":1.38,"P":0,"F":0,"co":0.0,"L":50,"fl":"MM0"},{"n":"MID-C DAY-AHEAD OFF-PEAK - ICE FUTURES ENERGY DIV","c":"064392","oi":31859,"mp":-1.0,"cp":0.3,"P":0,"F":0,"co":0.0,"L":50,"fl":""},{"n":"FUEL OIL-3% USGC/3.5% FOB RDAM BARGES - ICE FUTURES ENERGY DIV","c":"02141C","oi":31837,"mp":3.9,"cp":-0.87,"P":0,"F":0,"co":0.0,"L":50,"fl":""},{"n":"NYISO ZONE A DA PEAK - ICE FUTURES ENERGY DIV","c":"0643BY","oi":30543,"mp":-1.1,"cp":0.37,"P":0,"F":0,"co":0.0,"L":50,"fl":""},{"n":"CRUDE DIFF-TMX WCS 1A INDEX - ICE FUTURES ENERGY DIV","c":"06742G","oi":28732,"mp":0.0,"cp":0.0,"P":0,"F":0,"co":0.0,"L":50,"fl":"MM0"},{"n":"ALUMINUM MW US TR PLATTS - COMMODITY EXCHANGE INC.","c":"191693","oi":28444,"mp":0.2,"cp":0.38,"P":0,"F":0,"co":0.0,"L":50,"fl":""},{"n":"CHICAGO ETHANOL - NEW YORK MERCANTILE EXCHANGE","c":"025651","oi":27030,"mp":27.4,"cp":2.67,"P":-20,"F":20,"co":0.0,"L":50,"fl":""},{"n":"MISO IN. REAL-TIME OFF-PEAK - ICE FUTURES ENERGY DIV","c":"06439L","oi":25866,"mp":-2.3,"cp":0.06,"P":0,"F":0,"co":0.0,"L":50,"fl":""},{"n":"CHEESE (CASH-SETTLED) - CHICAGO MERCANTILE EXCHANGE","c":"063642","oi":24712,"mp":-0.8,"cp":-1.42,"P":0,"F":0,"co":0.0,"L":50,"fl":""},{"n":"RGGI VINTAGE 2020 - ICE FUTURES ENERGY DIV","c":"0063DJ","oi":24673,"mp":5.0,"cp":0.34,"P":0,"F":0,"co":0.0,"L":50,"fl":"ENV"},{"n":"NYISO ZONE J DA PEAK - ICE FUTURES ENERGY DIV","c":"0643BW","oi":24011,"mp":-1.0,"cp":-0.83,"P":0,"F":0,"co":0.0,"L":50,"fl":""},{"n":"MISO.INDIANA.HUB_month_on_dap - NODAL EXCHANGE","c":"064BFI","oi":23895,"mp":-4.9,"cp":0.4,"P":0,"F":0,"co":0.0,"L":50,"fl":""},{"n":"NYISO ZONE J DA OFF-PK - ICE FUTURES ENERGY DIV","c":"0643BX","oi":23805,"mp":0.3,"cp":-0.71,"P":0,"F":0,"co":0.0,"L":50,"fl":""},{"n":"MISO.INDIANA.HUB_month_off_dap - NODAL EXCHANGE","c":"064BFJ","oi":21675,"mp":-5.4,"cp":0.44,"P":0,"F":0,"co":0.0,"L":50,"fl":""},{"n":"NAT GASLNE OPIS MT B NONTET FP - ICE FUTURES ENERGY DIV","c":"06641A","oi":21612,"mp":0.0,"cp":-0.03,"P":0,"F":0,"co":0.0,"L":50,"fl":"MM0"},{"n":"PALO VERDE DA OFF-PK - ICE FUTURES ENERGY DIV","c":"0643CC","oi":21335,"mp":-1.2,"cp":0.01,"P":0,"F":0,"co":0.0,"L":50,"fl":""},{"n":"MILK, Class III - CHICAGO MERCANTILE EXCHANGE","c":"052641","oi":20953,"mp":-5.1,"cp":-1.6,"P":0,"F":0,"co":0.0,"L":50,"fl":""},{"n":"MASS COMPLIANCE RECs CLASS 1  - ICE FUTURES ENERGY DIV","c":"0063DL","oi":20373,"mp":-2.5,"cp":0.02,"P":0,"F":0,"co":0.0,"L":50,"fl":"ENV"},{"n":"CONWAY PROPANE (OPIS) - NEW YORK MERCANTILE EXCHANGE","c":"06665T","oi":20057,"mp":0.0,"cp":0.24,"P":0,"F":0,"co":0.0,"L":50,"fl":"MM0"},{"n":"PALO VERDE DA PEAK - ICE FUTURES ENERGY DIV","c":"0643CB","oi":19848,"mp":-2.0,"cp":0.34,"P":0,"F":0,"co":0.0,"L":50,"fl":""},{"n":"COAL (API 2) CIF ARA - NEW YORK MERCANTILE EXCHANGE","c":"024656","oi":19562,"mp":-4.4,"cp":1.24,"P":0,"F":0,"co":0.0,"L":50,"fl":""},{"n":"NYISO ZONE A DA OFF-PK - ICE FUTURES ENERGY DIV","c":"0643BZ","oi":18136,"mp":-7.5,"cp":-0.46,"P":0,"F":0,"co":0.0,"L":50,"fl":""},{"n":"PJM PSEG DAY-AHEAD PEAK - ICE FUTURES ENERGY DIV","c":"0643DL","oi":18014,"mp":1.7,"cp":1.14,"P":0,"F":0,"co":0.0,"L":50,"fl":""},{"n":"PJM PSEG ZONE DAY-AHEAD OFF-PEAK - ICE FUTURES ENERGY DIV","c":"0643DM","oi":14957,"mp":-3.2,"cp":1.08,"P":0,"F":0,"co":0.0,"L":50,"fl":""},{"n":"ERCOT N 345KV REAL T PK 2x16 - ICE FUTURES ENERGY DIV","c":"0643ID","oi":12648,"mp":3.6,"cp":-1.94,"P":0,"F":0,"co":0.0,"L":50,"fl":""},{"n":"CT RECs CLASS 1  - ICE FUTURES ENERGY DIV","c":"0063DK","oi":12088,"mp":-3.3,"cp":-1.2,"P":0,"F":0,"co":0.0,"L":50,"fl":"ENV"},{"n":"PJM PECO ZONE DA PEAK - ICE FUTURES ENERGY DIV","c":"0643CZ","oi":12011,"mp":0.0,"cp":-3.16,"P":0,"F":0,"co":0.0,"L":50,"fl":"MM0"},{"n":"FRZN CONCENTRATED ORANGE JUICE - ICE FUTURES U.S.","c":"040701","oi":11964,"mp":6.3,"cp":-2.7,"P":0,"F":0,"co":0.0,"L":50,"fl":""},{"n":"PJM PECO ZONE OFF-PEAK MONTHLY - ICE FUTURES ENERGY DIV","c":"0643D1","oi":11051,"mp":0.0,"cp":-0.71,"P":0,"F":0,"co":0.0,"L":50,"fl":"MM0"},{"n":"CRUDE DIFF-TMX SW 1A INDEX - ICE FUTURES ENERGY DIV","c":"06742T","oi":10894,"mp":0.0,"cp":0.0,"P":0,"F":0,"co":0.0,"L":50,"fl":"MM0"},{"n":"PJM BGE ZONE DAY AHEAD OFF PEAK MONTHLY - ICE FUTURES ENERGY DIV","c":"0643CJ","oi":8746,"mp":-6.6,"cp":0.86,"P":0,"F":0,"co":0.0,"L":50,"fl":""},{"n":"BUTANE OPIS MT BELV NONTET FP  - ICE FUTURES ENERGY DIV","c":"06641D","oi":7531,"mp":0.0,"cp":3.08,"P":0,"F":0,"co":0.0,"L":50,"fl":"MM0"},{"n":"USGC HSFO-PLATTS/BRENT 1ST LN  - ICE FUTURES ENERGY DIV","c":"02141R","oi":7408,"mp":0.0,"cp":0.08,"P":0,"F":0,"co":0.0,"L":50,"fl":"MM0"},{"n":"WCS OIL NET ENERGY MONTHLY IND - NEW YORK MERCANTILE EXCHANGE","c":"067A75","oi":7213,"mp":0.0,"cp":1.8,"P":0,"F":0,"co":0.0,"L":50,"fl":"MM0"},{"n":"GULF NO6 FO 3% v EUR 3.5% RDAM - NEW YORK MERCANTILE EXCHANGE","c":"021A28","oi":6255,"mp":0.0,"cp":-2.8,"P":0,"F":0,"co":0.0,"L":50,"fl":"MM0"},{"n":"NAPHTHA CRACK SPR - NEW YORK MERCANTILE EXCHANGE","c":"86665A","oi":6022,"mp":0.0,"cp":-4.82,"P":0,"F":0,"co":0.0,"L":50,"fl":"MM0"},{"n":"ETHANOL T2 FOB INCL DUTY - NEW YORK MERCANTILE EXCHANGE","c":"025608","oi":5930,"mp":0.0,"cp":-0.88,"P":0,"F":0,"co":0.0,"L":50,"fl":"MM0"},{"n":"CME MILK IV - CHICAGO MERCANTILE EXCHANGE","c":"052644","oi":5718,"mp":0.2,"cp":5.46,"P":0,"F":0,"co":0.0,"L":50,"fl":""},{"n":"ARGUS FAR EAST PROPANE - ICE FUTURES ENERGY DIV","c":"066413","oi":4218,"mp":0.0,"cp":-2.87,"P":0,"F":0,"co":0.0,"L":50,"fl":"MM0"},{"n":"ARGUS PROPANE FAR EAST INDEX - NEW YORK MERCANTILE EXCHANGE","c":"06665B","oi":4004,"mp":0.0,"cp":2.17,"P":0,"F":0,"co":0.0,"L":50,"fl":"MM0"},{"n":"MT BELVIEU LDH PROPANE BALMO  - NEW YORK MERCANTILE EXCHANGE","c":"06665W","oi":2440,"mp":0.0,"cp":-4.63,"P":0,"F":0,"co":0.0,"L":50,"fl":"MM0"},{"n":"CORN - CHICAGO BOARD OF TRADE","c":"002602","oi":1430281,"mp":-7.7,"cp":0.97,"P":0,"F":10,"co":2.5,"L":51,"fl":""},{"n":"NATURAL GAS - NEW YORK MERCANTILE EXCHANGE","c":"023651","oi":1205583,"mp":-3.4,"cp":0.96,"P":0,"F":10,"co":2.5,"L":51,"fl":""},{"n":"SUGAR NO. 11 - ICE FUTURES U.S.","c":"080732","oi":1019129,"mp":-3.0,"cp":1.37,"P":0,"F":10,"co":2.5,"L":51,"fl":""},{"n":"HENRY HUB - NEW YORK MERCANTILE EXCHANGE","c":"03565B","oi":732175,"mp":-0.1,"cp":0.31,"P":0,"F":10,"co":2.5,"L":51,"fl":""},{"n":"CRUDE OIL, LIGHT SWEET-WTI - ICE FUTURES EUROPE","c":"067411","oi":647309,"mp":5.4,"cp":1.69,"P":0,"F":10,"co":2.5,"L":51,"fl":""},{"n":"WHEAT-SRW - CHICAGO BOARD OF TRADE","c":"001602","oi":370416,"mp":7.4,"cp":2.35,"P":0,"F":10,"co":2.5,"L":51,"fl":""},{"n":"LIVE CATTLE - CHICAGO MERCANTILE EXCHANGE","c":"057642","oi":265359,"mp":-0.9,"cp":0.56,"P":0,"F":10,"co":2.5,"L":51,"fl":""},{"n":"COCOA - ICE FUTURES U.S.","c":"073732","oi":214059,"mp":-4.2,"cp":1.02,"P":0,"F":10,"co":2.5,"L":51,"fl":""},{"n":"TRANSCONTINENTAL GAS- STATION 85 (ZONE 4) - ICE FUTURES ENERGY DIV","c":"0233CW","oi":172120,"mp":0.0,"cp":0.33,"P":0,"F":10,"co":2.5,"L":51,"fl":"MM0"},{"n":"PJM.WESTERN HUB_month_on_dap - NODAL EXCHANGE","c":"064FHK","oi":167211,"mp":-8.2,"cp":1.95,"P":0,"F":10,"co":2.5,"L":51,"fl":""},{"n":"MT BELVIEU LDH PROPANE (OPIS) - NEW YORK MERCANTILE EXCHANGE","c":"06665O","oi":129458,"mp":-0.1,"cp":0.88,"P":0,"F":10,"co":2.5,"L":51,"fl":""},{"n":"TRANSCO LEIDY BASIS - ICE FUTURES ENERGY DIV","c":"0233DT","oi":96498,"mp":0.0,"cp":0.78,"P":0,"F":10,"co":2.5,"L":51,"fl":"MM0"},{"n":"WHEAT-HRSpring - MINNEAPOLIS GRAIN EXCHANGE","c":"001626","oi":73879,"mp":-18.0,"cp":-0.23,"P":10,"F":0,"co":2.5,"L":51,"fl":""},{"n":"ISO NE MASS HUB DA OFF-PK - ICE FUTURES ENERGY DIV","c":"0643BF","oi":72494,"mp":-0.1,"cp":0.95,"P":0,"F":10,"co":2.5,"L":51,"fl":""},{"n":"PJM.AEP-DAYTON HUB_month_on_rtp - NODAL EXCHANGE","c":"064FKA","oi":62860,"mp":-14.1,"cp":-0.63,"P":10,"F":0,"co":2.5,"L":51,"fl":""},{"n":"PROPANE NON-LDH MT BEL - NEW YORK MERCANTILE EXCHANGE","c":"06665G","oi":57423,"mp":0.0,"cp":1.08,"P":0,"F":10,"co":2.5,"L":51,"fl":"MM0"},{"n":"NORTHWEST PIPELINE CORP. - ROCKY MOUNTAINS - ICE FUTURES ENERGY DIV","c":"0233BD","oi":56507,"mp":0.0,"cp":2.07,"P":0,"F":10,"co":2.5,"L":51,"fl":"MM0"},{"n":"PJM.AEP-DAYTON HUB_month_off_rtp - NODAL EXCHANGE","c":"064FKB","oi":55789,"mp":-18.1,"cp":-0.37,"P":10,"F":0,"co":2.5,"L":51,"fl":""},{"n":"PJM.N ILLINOIS HUB_month_off_dap - NODAL EXCHANGE","c":"064ERN","oi":51096,"mp":23.3,"cp":3.76,"P":-10,"F":20,"co":2.5,"L":51,"fl":""},{"n":"PJM.N ILLINOIS HUB_month_on_dap - NODAL EXCHANGE","c":"064ERM","oi":48191,"mp":24.4,"cp":3.51,"P":-10,"F":20,"co":2.5,"L":51,"fl":""},{"n":"PJM.PEPCO_month_off_dap - NODAL EXCHANGE","c":"064EVH","oi":19825,"mp":-23.7,"cp":-2.45,"P":10,"F":0,"co":2.5,"L":51,"fl":""},{"n":"PJM BGE ZONE DAY AHEAD, PEAK MONTHLY - ICE FUTURES ENERGY DIV","c":"0643CK","oi":8966,"mp":-10.0,"cp":2.84,"P":10,"F":0,"co":2.5,"L":51,"fl":""},{"n":"CHICAGO FIN BASIS - ICE FUTURES ENERGY DIV","c":"023397","oi":376787,"mp":-0.2,"cp":0.89,"P":0,"F":20,"co":5.0,"L":53,"fl":""},{"n":"TETCO M2 Basis (Receipts) - ICE FUTURES ENERGY DIV","c":"0233DR","oi":260966,"mp":0.0,"cp":0.4,"P":0,"F":20,"co":5.0,"L":53,"fl":"MM0"},{"n":"ARGUS WTI Mid/WTI TRADE MONTH - ICE FUTURES ENERGY DIV","c":"06742U","oi":238038,"mp":1.1,"cp":2.17,"P":0,"F":20,"co":5.0,"L":53,"fl":""},{"n":"HENRY HUB - TAILGATE LOUISIANA (INDEX) - ICE FUTURES ENERGY DIV","c":"0233AH","oi":234225,"mp":2.0,"cp":2.79,"P":0,"F":20,"co":5.0,"L":53,"fl":""},{"n":"EL PASO-SAN JUAN BASIN-BLANCO POOL PRIMARY ONLY-BASIS - ICE FUTURES ENERGY DIV","c":"0233A8","oi":120984,"mp":0.0,"cp":1.62,"P":0,"F":20,"co":5.0,"L":53,"fl":"MM0"},{"n":"PJM.PPL_month_on_dap - NODAL EXCHANGE","c":"064EWU","oi":72660,"mp":-20.7,"cp":1.38,"P":10,"F":10,"co":5.0,"L":53,"fl":""},{"n":"PJM.PPL_month_off_dap - NODAL EXCHANGE","c":"064EWV","oi":67165,"mp":-22.4,"cp":1.67,"P":10,"F":10,"co":5.0,"L":53,"fl":""},{"n":"MT BELV NORM BUTANE OPIS - NEW YORK MERCANTILE EXCHANGE","c":"06665Q","oi":54491,"mp":0.3,"cp":3.57,"P":0,"F":20,"co":5.0,"L":53,"fl":""},{"n":"WAHA HUB - WEST TEXAS DELIVERED/BUYER'S INDEX - ICE FUTURES ENERGY DIV","c":"0233D4","oi":44518,"mp":0.0,"cp":2.2,"P":0,"F":20,"co":5.0,"L":53,"fl":"MM0"},{"n":"GULF JET NY HEAT OIL SPR - NEW YORK MERCANTILE EXCHANGE","c":"86465A","oi":20048,"mp":-0.8,"cp":2.67,"P":0,"F":20,"co":5.0,"L":53,"fl":""},{"n":"GULF # 6 FUEL 3.0% SULFUR - NEW YORK MERCANTILE EXCHANGE","c":"02165A","oi":16388,"mp":0.6,"cp":3.96,"P":0,"F":20,"co":5.0,"L":53,"fl":""},{"n":"CALIF CARBON ALL VINTAGE 2018 - ICE FUTURES ENERGY DIV","c":"0063A2","oi":13337,"mp":13.5,"cp":7.86,"P":-10,"F":30,"co":5.0,"L":53,"fl":"ENV"},{"n":"PJM WH REAL TIME PEAK - ICE FUTURES ENERGY DIV","c":"064363","oi":10110,"mp":18.6,"cp":5.66,"P":-10,"F":30,"co":5.0,"L":53,"fl":""},{"n":"RANDOM LENGTH LUMBER - CHICAGO MERCANTILE EXCHANGE","c":"058643","oi":2805,"mp":-27.9,"cp":4.03,"P":20,"F":0,"co":5.0,"L":53,"fl":""},{"n":"SOYBEAN MEAL - CHICAGO BOARD OF TRADE","c":"026603","oi":399650,"mp":7.9,"cp":4.42,"P":0,"F":30,"co":7.5,"L":54,"fl":""},{"n":"HENRY HUB - TAILGATE LOUISIANA (BASIS) - ICE FUTURES ENERGY DIV","c":"0233AG","oi":220938,"mp":0.0,"cp":4.44,"P":0,"F":30,"co":7.5,"L":54,"fl":"MM0"},{"n":"WTI FINANCIAL CRUDE OIL - NEW YORK MERCANTILE EXCHANGE","c":"06765A","oi":169482,"mp":-4.6,"cp":6.62,"P":0,"F":30,"co":7.5,"L":54,"fl":""},{"n":"UP DOWN GC ULSD VS HO SPR - NEW YORK MERCANTILE EXCHANGE","c":"022A13","oi":46271,"mp":0.0,"cp":3.58,"P":0,"F":30,"co":7.5,"L":54,"fl":"MM0"},{"n":"DOMINION - SOUTH POINT - ICE FUTURES ENERGY DIV","c":"0233A2","oi":42930,"mp":2.8,"cp":13.15,"P":0,"F":30,"co":7.5,"L":54,"fl":""},{"n":"PROPANE OPIS MT BELV NONTET FP - ICE FUTURES ENERGY DIV","c":"06641F","oi":38555,"mp":0.0,"cp":4.22,"P":0,"F":30,"co":7.5,"L":54,"fl":"MM0"},{"n":"NYISO.WEST_month_on_dap - NODAL EXCHANGE","c":"064DEU","oi":28150,"mp":-52.9,"cp":-1.49,"P":30,"F":0,"co":7.5,"L":54,"fl":""},{"n":"HOT ROLLED COIL STEEL - NEW YORK MERCANTILE EXCHANGE","c":"192651","oi":23807,"mp":-21.0,"cp":3.16,"P":10,"F":20,"co":7.5,"L":54,"fl":""}]}